{
  "_meta": {
    "fetched_at": "2026-03-05T06:47:57Z",
    "source": "derived+rest",
    "derivation": "earliest commit per author_login from commits.json; enrich via /commits/{sha} for files/stats",
    "owner": "ros2",
    "repo": "tlsf"
  },
  "data": [
    {
      "author": "clalancette",
      "date": "2018-06-26T00:26:37Z",
      "sha": "f39a63938625d464330187895541bcf5859bd0db",
      "message": "Change maintainer to me. (#6)\n\nSigned-off-by: Chris Lalancette <clalancette@openrobotics.org>",
      "files_changed": 1,
      "additions": 2,
      "deletions": 1,
      "commit_type": "config",
      "files": [
        {
          "sha": "de85ee3a55b64073e919e9ba549a55277ee1df9e",
          "filename": "tlsf/package.xml",
          "status": "modified",
          "additions": 2,
          "deletions": 1,
          "changes": 3,
          "blob_url": "https://github.com/ros2/tlsf/blob/f39a63938625d464330187895541bcf5859bd0db/tlsf%2Fpackage.xml",
          "raw_url": "https://github.com/ros2/tlsf/raw/f39a63938625d464330187895541bcf5859bd0db/tlsf%2Fpackage.xml",
          "contents_url": "https://api.github.com/repos/ros2/tlsf/contents/tlsf%2Fpackage.xml?ref=f39a63938625d464330187895541bcf5859bd0db",
          "patch": "@@ -4,7 +4,8 @@\n   <name>tlsf</name>\n   <version>0.4.0</version>\n   <description>TLSF allocator version 2.4.6</description>\n-  <maintainer email=\"jackie@osrfoundation.org\">Jackie Kay</maintainer>\n+  <author email=\"jackie@osrfoundation.org\">Jackie Kay</author>\n+  <maintainer email=\"clalancette@openrobotics.org\">Chris Lalancette</maintainer>\n   <license>GNU Lesser Public License 2.1</license>\n \n   <buildtool_depend>ament_cmake</buildtool_depend>"
        }
      ]
    },
    {
      "author": "mosfet80",
      "date": "2025-05-14T21:37:04Z",
      "sha": "24c573594074da530c8845634ec6d01f1acfb8c0",
      "message": "update cmake requirements (#18)\n\nSigned-off-by: mosfet80 <10235105+mosfet80@users.noreply.github.com>\nCo-authored-by: Alejandro Hernández Cordero <ahcorde@gmail.com>",
      "files_changed": 1,
      "additions": 1,
      "deletions": 1,
      "commit_type": "docs",
      "files": [
        {
          "sha": "2de28675b484dc1e262ea5e52bfda1750ca9996f",
          "filename": "tlsf/CMakeLists.txt",
          "status": "modified",
          "additions": 1,
          "deletions": 1,
          "changes": 2,
          "blob_url": "https://github.com/ros2/tlsf/blob/24c573594074da530c8845634ec6d01f1acfb8c0/tlsf%2FCMakeLists.txt",
          "raw_url": "https://github.com/ros2/tlsf/raw/24c573594074da530c8845634ec6d01f1acfb8c0/tlsf%2FCMakeLists.txt",
          "contents_url": "https://api.github.com/repos/ros2/tlsf/contents/tlsf%2FCMakeLists.txt?ref=24c573594074da530c8845634ec6d01f1acfb8c0",
          "patch": "@@ -1,4 +1,4 @@\n-cmake_minimum_required(VERSION 3.5)\n+cmake_minimum_required(VERSION 3.20)\n \n project(tlsf)\n "
        }
      ]
    },
    {
      "author": "cottsay",
      "date": "2025-04-26T02:54:58Z",
      "sha": "a5baa9edc2909feaca193cad5f6051fc9e360429",
      "message": "0.11.0",
      "files_changed": 2,
      "additions": 4,
      "deletions": 1,
      "commit_type": "config",
      "files": [
        {
          "sha": "5a1ac8b0f670d0f6525f25e907c91b1a2280c369",
          "filename": "tlsf/CHANGELOG.rst",
          "status": "modified",
          "additions": 3,
          "deletions": 0,
          "changes": 3,
          "blob_url": "https://github.com/ros2/tlsf/blob/a5baa9edc2909feaca193cad5f6051fc9e360429/tlsf%2FCHANGELOG.rst",
          "raw_url": "https://github.com/ros2/tlsf/raw/a5baa9edc2909feaca193cad5f6051fc9e360429/tlsf%2FCHANGELOG.rst",
          "contents_url": "https://api.github.com/repos/ros2/tlsf/contents/tlsf%2FCHANGELOG.rst?ref=a5baa9edc2909feaca193cad5f6051fc9e360429",
          "patch": "@@ -2,6 +2,9 @@\n Changelog for package tlsf\n ^^^^^^^^^^^^^^^^^^^^^^^^^^\n \n+0.11.0 (2025-04-25)\n+-------------------\n+\n 0.10.1 (2024-10-03)\n -------------------\n * Fixed link (`#15 <https://github.com/ros2/tlsf/issues/15>`_)"
        },
        {
          "sha": "492a17aa406a596e3885064f83b1b24d76dbfbbe",
          "filename": "tlsf/package.xml",
          "status": "modified",
          "additions": 1,
          "deletions": 1,
          "changes": 2,
          "blob_url": "https://github.com/ros2/tlsf/blob/a5baa9edc2909feaca193cad5f6051fc9e360429/tlsf%2Fpackage.xml",
          "raw_url": "https://github.com/ros2/tlsf/raw/a5baa9edc2909feaca193cad5f6051fc9e360429/tlsf%2Fpackage.xml",
          "contents_url": "https://api.github.com/repos/ros2/tlsf/contents/tlsf%2Fpackage.xml?ref=a5baa9edc2909feaca193cad5f6051fc9e360429",
          "patch": "@@ -2,7 +2,7 @@\n <?xml-model href=\"http://download.ros.org/schema/package_format2.xsd\" schematypens=\"http://www.w3.org/2001/XMLSchema\"?>\n <package format=\"2\">\n   <name>tlsf</name>\n-  <version>0.10.1</version>\n+  <version>0.11.0</version>\n   <description>TLSF allocator version 2.4.6</description>\n \n   <maintainer email=\"brandon@openrobotics.org\">Brandon Ong</maintainer>"
        }
      ]
    },
    {
      "author": "ahcorde",
      "date": "2024-08-21T12:03:42Z",
      "sha": "4dd0e3333c12d1c08474e9f4c10a25e2b531d03e",
      "message": "Fixed link (#15)\n\nSigned-off-by: Alejandro Hernández Cordero <ahcorde@gmail.com>",
      "files_changed": 1,
      "additions": 1,
      "deletions": 1,
      "commit_type": "docs",
      "files": [
        {
          "sha": "23fc85ff440bacdbfc33963b5534a5c81358010c",
          "filename": "tlsf/README.md",
          "status": "modified",
          "additions": 1,
          "deletions": 1,
          "changes": 2,
          "blob_url": "https://github.com/ros2/tlsf/blob/4dd0e3333c12d1c08474e9f4c10a25e2b531d03e/tlsf%2FREADME.md",
          "raw_url": "https://github.com/ros2/tlsf/raw/4dd0e3333c12d1c08474e9f4c10a25e2b531d03e/tlsf%2FREADME.md",
          "contents_url": "https://api.github.com/repos/ros2/tlsf/contents/tlsf%2FREADME.md?ref=4dd0e3333c12d1c08474e9f4c10a25e2b531d03e",
          "patch": "@@ -1,3 +1,3 @@\n-This package contains a snapshot of TLSF version 2.4.6 downloaded as a .tar from: http://www.gii.upv.es/tlsf/main/repo\n+This package contains a snapshot of TLSF version 2.4.6 downloaded as a .tar from: [http://www.gii.upv.es/tlsf/main/repo.html](http://www.gii.upv.es/tlsf/main/repo.html)\n \n Github repository: https://github.com/emeryberger/Malloc-Implementations/tree/master/allocators/TLSF/TLSF-2.4.6"
        }
      ]
    },
    {
      "author": "marcoag",
      "date": "2024-04-29T08:29:57Z",
      "sha": "cece1e535ba04e1f51864723271e06796f817c1d",
      "message": "Changelog.\n\nSigned-off-by: Marco A. Gutierrez <marcogg@marcogg.com>",
      "files_changed": 1,
      "additions": 3,
      "deletions": 0,
      "commit_type": "docs",
      "files": [
        {
          "sha": "b102a0459a141ae81000df3bc11cceb1bd207acc",
          "filename": "tlsf/CHANGELOG.rst",
          "status": "modified",
          "additions": 3,
          "deletions": 0,
          "changes": 3,
          "blob_url": "https://github.com/ros2/tlsf/blob/cece1e535ba04e1f51864723271e06796f817c1d/tlsf%2FCHANGELOG.rst",
          "raw_url": "https://github.com/ros2/tlsf/raw/cece1e535ba04e1f51864723271e06796f817c1d/tlsf%2FCHANGELOG.rst",
          "contents_url": "https://api.github.com/repos/ros2/tlsf/contents/tlsf%2FCHANGELOG.rst?ref=cece1e535ba04e1f51864723271e06796f817c1d",
          "patch": "@@ -2,6 +2,9 @@\n Changelog for package tlsf\n ^^^^^^^^^^^^^^^^^^^^^^^^^^\n \n+Forthcoming\n+-----------\n+\n 0.9.0 (2023-04-28)\n ------------------\n "
        }
      ]
    },
    {
      "author": "audrow",
      "date": "2020-09-22T18:07:04Z",
      "sha": "193c425e35f64030be514687a65a3cbddd614466",
      "message": "Enable basic warnings (#8)\n\n* Add compiler warnings\r\n\r\nSigned-off-by: Audrow Nash <audrow.nash@gmail.com>\r\n\r\n* Fix variadic macro warnings\r\n\r\nSigned-off-by: Audrow Nash <audrow.nash@gmail.com>\r\n\r\n* Void cast unused parameters\r\n\r\nSigned-off-by: Audrow Nash <audrow.nash@gmail.com>\r\n\r\n* Fix left shift of negative value warning\r\n\r\nSigned-off-by: Audrow Nash <audrow.nash@gmail.com>\r\n\r\n* Update CMakeLists to treat as C project\r\n\r\nSigned-off-by: Audrow Nash <audrow.nash@gmail.com>\r\n\r\n* Update CMake variables\r\n\r\nSigned-off-by: Audrow Nash <audrow.nash@gmail.com>",
      "files_changed": 2,
      "additions": 16,
      "deletions": 6,
      "commit_type": "code",
      "files": [
        {
          "sha": "d1646f6fe7388a60cc13ee1409ba705b56ac5795",
          "filename": "tlsf/CMakeLists.txt",
          "status": "modified",
          "additions": 8,
          "deletions": 0,
          "changes": 8,
          "blob_url": "https://github.com/ros2/tlsf/blob/193c425e35f64030be514687a65a3cbddd614466/tlsf%2FCMakeLists.txt",
          "raw_url": "https://github.com/ros2/tlsf/raw/193c425e35f64030be514687a65a3cbddd614466/tlsf%2FCMakeLists.txt",
          "contents_url": "https://api.github.com/repos/ros2/tlsf/contents/tlsf%2FCMakeLists.txt?ref=193c425e35f64030be514687a65a3cbddd614466",
          "patch": "@@ -7,6 +7,14 @@ if(WIN32 OR APPLE OR ANDROID)\n   return()\n endif()\n \n+# Default to C11\n+if(NOT CMAKE_C_STANDARD)\n+  set(CMAKE_C_STANDARD 11)\n+endif()\n+if(CMAKE_COMPILER_IS_GNUCC OR CMAKE_C_COMPILER_ID MATCHES \"Clang\")\n+  add_compile_options(-Wall -Wextra -Wpedantic)\n+endif()\n+\n find_package(ament_cmake REQUIRED)\n \n include_directories(include/tlsf)"
        },
        {
          "sha": "f3b00c7960cb64d180b6523e1e7c46e974a15222",
          "filename": "tlsf/src/tlsf.c",
          "status": "modified",
          "additions": 8,
          "deletions": 6,
          "changes": 14,
          "blob_url": "https://github.com/ros2/tlsf/blob/193c425e35f64030be514687a65a3cbddd614466/tlsf%2Fsrc%2Ftlsf.c",
          "raw_url": "https://github.com/ros2/tlsf/raw/193c425e35f64030be514687a65a3cbddd614466/tlsf%2Fsrc%2Ftlsf.c",
          "contents_url": "https://api.github.com/repos/ros2/tlsf/contents/tlsf%2Fsrc%2Ftlsf.c?ref=193c425e35f64030be514687a65a3cbddd614466",
          "patch": "@@ -174,14 +174,14 @@ extern \"C\"\n \n #ifdef USE_PRINTF\n #include <stdio.h>\n-# define PRINT_MSG(fmt, args...) printf(fmt, ## args)\n-# define ERROR_MSG(fmt, args...) printf(fmt, ## args)\n+# define PRINT_MSG(fmt, ...) printf(fmt, ## __VA_ARGS__)\n+# define ERROR_MSG(fmt, ...) printf(fmt, ## __VA_ARGS__)\n #else\n # if !defined(PRINT_MSG)\n-#  define PRINT_MSG(fmt, args...)\n+#  define PRINT_MSG(fmt, ...)\n # endif\n # if !defined(ERROR_MSG)\n-#  define ERROR_MSG(fmt, args...)\n+#  define ERROR_MSG(fmt, ...)\n # endif\n #endif\n \n@@ -347,14 +347,14 @@ static __inline__ void MAPPING_INSERT(size_t _r, int *_fl, int *_sl)\n \n static __inline__ bhdr_t *FIND_SUITABLE_BLOCK(tlsf_t * _tlsf, int *_fl, int *_sl)\n {\n-    u32_t _tmp = _tlsf->sl_bitmap[*_fl] & (~0 << *_sl);\n+    u32_t _tmp = _tlsf->sl_bitmap[*_fl] & (~0u << *_sl);\n     bhdr_t *_b = NULL;\n \n     if (_tmp) {\n         *_sl = ls_bit(_tmp);\n         _b = _tlsf->matrix[*_fl][*_sl];\n     } else {\n-        *_fl = ls_bit(_tlsf->fl_bitmap & (~0 << (*_fl + 1)));\n+        *_fl = ls_bit(_tlsf->fl_bitmap & (~0u << (*_fl + 1)));\n         if (*_fl > 0) {         /* likely */\n             *_sl = ls_bit(_tlsf->sl_bitmap[*_fl]);\n             _b = _tlsf->matrix[*_fl][*_sl];\n@@ -588,6 +588,7 @@ size_t add_new_area(void *area, size_t area_size, void *mem_pool)\n size_t get_used_size(void *mem_pool)\n {\n /******************************************************************/\n+    (void) mem_pool;\n #if TLSF_STATISTIC\n     return ((tlsf_t *) mem_pool)->used_size;\n #else\n@@ -599,6 +600,7 @@ size_t get_used_size(void *mem_pool)\n size_t get_max_size(void *mem_pool)\n {\n /******************************************************************/\n+    (void) mem_pool;\n #if TLSF_STATISTIC\n     return ((tlsf_t *) mem_pool)->max_size;\n #else"
        }
      ]
    },
    {
      "author": "paudrow",
      "date": "2022-05-04T21:39:59Z",
      "sha": "2c42d5724d07d0d85b6f486fd863bc20d5cf9b2b",
      "message": "0.8.0\n\nSigned-off-by: Audrow Nash <audrow@hey.com>",
      "files_changed": 2,
      "additions": 4,
      "deletions": 1,
      "commit_type": "config",
      "files": [
        {
          "sha": "a3b006bc4a6272c571799da41356a40b5e7dd40f",
          "filename": "tlsf/CHANGELOG.rst",
          "status": "modified",
          "additions": 3,
          "deletions": 0,
          "changes": 3,
          "blob_url": "https://github.com/ros2/tlsf/blob/2c42d5724d07d0d85b6f486fd863bc20d5cf9b2b/tlsf%2FCHANGELOG.rst",
          "raw_url": "https://github.com/ros2/tlsf/raw/2c42d5724d07d0d85b6f486fd863bc20d5cf9b2b/tlsf%2FCHANGELOG.rst",
          "contents_url": "https://api.github.com/repos/ros2/tlsf/contents/tlsf%2FCHANGELOG.rst?ref=2c42d5724d07d0d85b6f486fd863bc20d5cf9b2b",
          "patch": "@@ -2,6 +2,9 @@\n Changelog for package tlsf\n ^^^^^^^^^^^^^^^^^^^^^^^^^^\n \n+0.8.0 (2022-05-04)\n+------------------\n+\n 0.7.0 (2022-03-01)\n ------------------\n * Install headers to include/${PROJECT_NAME} (`#11 <https://github.com/ros2/tlsf/issues/11>`_)"
        },
        {
          "sha": "82c368544c57fb33123d419c4cbec8c9d4e6b5c2",
          "filename": "tlsf/package.xml",
          "status": "modified",
          "additions": 1,
          "deletions": 1,
          "changes": 2,
          "blob_url": "https://github.com/ros2/tlsf/blob/2c42d5724d07d0d85b6f486fd863bc20d5cf9b2b/tlsf%2Fpackage.xml",
          "raw_url": "https://github.com/ros2/tlsf/raw/2c42d5724d07d0d85b6f486fd863bc20d5cf9b2b/tlsf%2Fpackage.xml",
          "contents_url": "https://api.github.com/repos/ros2/tlsf/contents/tlsf%2Fpackage.xml?ref=2c42d5724d07d0d85b6f486fd863bc20d5cf9b2b",
          "patch": "@@ -2,7 +2,7 @@\n <?xml-model href=\"http://download.ros.org/schema/package_format2.xsd\" schematypens=\"http://www.w3.org/2001/XMLSchema\"?>\n <package format=\"2\">\n   <name>tlsf</name>\n-  <version>0.7.0</version>\n+  <version>0.8.0</version>\n   <description>TLSF allocator version 2.4.6</description>\n   <maintainer email=\"clalancette@openrobotics.org\">Chris Lalancette</maintainer>\n   <license>GNU Lesser Public License 2.1</license>"
        }
      ]
    },
    {
      "author": "methylDragon",
      "date": "2022-05-06T17:45:28Z",
      "sha": "6c33f5ebba5a4320b8404f26571a98be66514b07",
      "message": "Update maintainers (#12)\n\nSigned-off-by: methylDragon <methylDragon@gmail.com>",
      "files_changed": 1,
      "additions": 2,
      "deletions": 1,
      "commit_type": "config",
      "files": [
        {
          "sha": "5884b63694c6383a83133115a96cede3950f42d0",
          "filename": "tlsf/package.xml",
          "status": "modified",
          "additions": 2,
          "deletions": 1,
          "changes": 3,
          "blob_url": "https://github.com/ros2/tlsf/blob/6c33f5ebba5a4320b8404f26571a98be66514b07/tlsf%2Fpackage.xml",
          "raw_url": "https://github.com/ros2/tlsf/raw/6c33f5ebba5a4320b8404f26571a98be66514b07/tlsf%2Fpackage.xml",
          "contents_url": "https://api.github.com/repos/ros2/tlsf/contents/tlsf%2Fpackage.xml?ref=6c33f5ebba5a4320b8404f26571a98be66514b07",
          "patch": "@@ -4,9 +4,10 @@\n   <name>tlsf</name>\n   <version>0.8.0</version>\n   <description>TLSF allocator version 2.4.6</description>\n-  <maintainer email=\"clalancette@openrobotics.org\">Chris Lalancette</maintainer>\n+  <maintainer email=\"brandon@openrobotics.org\">Brandon Ong</maintainer>\n   <license>GNU Lesser Public License 2.1</license>\n   <author email=\"jackie@osrfoundation.org\">Jackie Kay</author>\n+  <author email=\"clalancette@openrobotics.org\">Chris Lalancette</author>\n \n   <buildtool_depend>ament_cmake</buildtool_depend>\n "
        }
      ]
    },
    {
      "author": "sloretz",
      "date": "2021-12-06T17:41:49Z",
      "sha": "d3d744ad2dd825715af0b54e24677518ba67aca4",
      "message": "Export a modern CMake target instead of old-style variables (#10)\n\nSigned-off-by: Shane Loretz <sloretz@osrfoundation.org>",
      "files_changed": 1,
      "additions": 6,
      "deletions": 8,
      "commit_type": "docs",
      "files": [
        {
          "sha": "d24151998d665d66714074bd3848f501a2f6453d",
          "filename": "tlsf/CMakeLists.txt",
          "status": "modified",
          "additions": 6,
          "deletions": 8,
          "changes": 14,
          "blob_url": "https://github.com/ros2/tlsf/blob/d3d744ad2dd825715af0b54e24677518ba67aca4/tlsf%2FCMakeLists.txt",
          "raw_url": "https://github.com/ros2/tlsf/raw/d3d744ad2dd825715af0b54e24677518ba67aca4/tlsf%2FCMakeLists.txt",
          "contents_url": "https://api.github.com/repos/ros2/tlsf/contents/tlsf%2FCMakeLists.txt?ref=d3d744ad2dd825715af0b54e24677518ba67aca4",
          "patch": "@@ -17,16 +17,13 @@ endif()\n \n find_package(ament_cmake REQUIRED)\n \n-include_directories(include/tlsf)\n add_library(${PROJECT_NAME} STATIC src/tlsf.c src/target.h include/tlsf/tlsf.h)\n+target_include_directories(${PROJECT_NAME} PUBLIC\n+  \"$<BUILD_INTERFACE:${CMAKE_SOURCE_DIR}/include/tlsf>\"\n+  \"$<INSTALL_INTERFACE:include>\")\n+set_target_properties(${PROJECT_NAME} PROPERTIES C_VISIBILITY_PRESET hidden)\n \n-set_target_properties(${PROJECT_NAME}\n-  PROPERTIES\n-    COMPILE_FLAGS \"-fvisibility=hidden\"\n-)\n-\n-ament_export_include_directories(include)\n-ament_export_libraries(${PROJECT_NAME})\n+ament_export_targets(export_${PROJECT_NAME})\n \n # Disable linting for now.\n #if(BUILD_TESTING)\n@@ -42,6 +39,7 @@ install(DIRECTORY include/\n \n install(\n   TARGETS ${PROJECT_NAME}\n+  EXPORT export_${PROJECT_NAME}\n   ARCHIVE DESTINATION lib\n   LIBRARY DESTINATION lib\n   RUNTIME DESTINATION bin"
        }
      ]
    },
    {
      "author": "mikaelarguedas",
      "date": "2017-12-09T01:24:54Z",
      "sha": "009939fc3252856e768f8c3d5d43959063b517c6",
      "message": "0.4.0",
      "files_changed": 1,
      "additions": 1,
      "deletions": 1,
      "commit_type": "config",
      "files": [
        {
          "sha": "5d0ceb50d56499baf7bb55fae95cbb812bcbe50e",
          "filename": "tlsf/package.xml",
          "status": "modified",
          "additions": 1,
          "deletions": 1,
          "changes": 2,
          "blob_url": "https://github.com/ros2/tlsf/blob/009939fc3252856e768f8c3d5d43959063b517c6/tlsf%2Fpackage.xml",
          "raw_url": "https://github.com/ros2/tlsf/raw/009939fc3252856e768f8c3d5d43959063b517c6/tlsf%2Fpackage.xml",
          "contents_url": "https://api.github.com/repos/ros2/tlsf/contents/tlsf%2Fpackage.xml?ref=009939fc3252856e768f8c3d5d43959063b517c6",
          "patch": "@@ -2,7 +2,7 @@\n <?xml-model href=\"http://download.ros.org/schema/package_format2.xsd\" schematypens=\"http://www.w3.org/2001/XMLSchema\"?>\n <package format=\"2\">\n   <name>tlsf</name>\n-  <version>0.0.3</version>\n+  <version>0.4.0</version>\n   <description>TLSF allocator version 2.4.6</description>\n   <maintainer email=\"jackie@osrfoundation.org\">Jackie Kay</maintainer>\n   <license>GNU Lesser Public License 2.1</license>"
        }
      ]
    },
    {
      "author": "dirk-thomas",
      "date": "2016-04-21T17:49:20Z",
      "sha": "8323b7c080cac18e6ca69ee1af911507139a9717",
      "message": "remove -fvisibility-inlines-hidden\n\n> warning: command line option ‘-fvisibility-inlines-hidden’ is valid for C++/ObjC++ but not for C",
      "files_changed": 1,
      "additions": 1,
      "deletions": 1,
      "commit_type": "docs",
      "files": [
        {
          "sha": "a6994ee6d5a3da68c29b6b5305120cad8bc2ba1a",
          "filename": "tlsf/CMakeLists.txt",
          "status": "modified",
          "additions": 1,
          "deletions": 1,
          "changes": 2,
          "blob_url": "https://github.com/ros2/tlsf/blob/8323b7c080cac18e6ca69ee1af911507139a9717/tlsf%2FCMakeLists.txt",
          "raw_url": "https://github.com/ros2/tlsf/raw/8323b7c080cac18e6ca69ee1af911507139a9717/tlsf%2FCMakeLists.txt",
          "contents_url": "https://api.github.com/repos/ros2/tlsf/contents/tlsf%2FCMakeLists.txt?ref=8323b7c080cac18e6ca69ee1af911507139a9717",
          "patch": "@@ -14,7 +14,7 @@ add_library(${PROJECT_NAME} STATIC src/tlsf.c src/target.h include/tlsf/tlsf.h)\n \n set_target_properties(${PROJECT_NAME}\n   PROPERTIES\n-    COMPILE_FLAGS \"-fvisibility=hidden -fvisibility-inlines-hidden\"\n+    COMPILE_FLAGS \"-fvisibility=hidden\"\n )\n \n ament_export_include_directories(include)"
        }
      ]
    },
    {
      "author": "esteve",
      "date": "2016-06-10T02:25:02Z",
      "sha": "fb41db3854ac9f23a6091b54d80f8c8493bc60bb",
      "message": "Disable on Android (#3)",
      "files_changed": 1,
      "additions": 2,
      "deletions": 2,
      "commit_type": "docs",
      "files": [
        {
          "sha": "1015418c66f9159fb7ecfd28c7824e4369c826eb",
          "filename": "tlsf/CMakeLists.txt",
          "status": "modified",
          "additions": 2,
          "deletions": 2,
          "changes": 4,
          "blob_url": "https://github.com/ros2/tlsf/blob/fb41db3854ac9f23a6091b54d80f8c8493bc60bb/tlsf%2FCMakeLists.txt",
          "raw_url": "https://github.com/ros2/tlsf/raw/fb41db3854ac9f23a6091b54d80f8c8493bc60bb/tlsf%2FCMakeLists.txt",
          "contents_url": "https://api.github.com/repos/ros2/tlsf/contents/tlsf%2FCMakeLists.txt?ref=fb41db3854ac9f23a6091b54d80f8c8493bc60bb",
          "patch": "@@ -2,8 +2,8 @@ cmake_minimum_required(VERSION 2.8.3)\n \n project(tlsf)\n \n-if(WIN32 OR APPLE)\n-  message(STATUS \"tlsf allocator does not target Windows or OSX, skipping...\")\n+if(WIN32 OR APPLE OR ANDROID)\n+  message(STATUS \"tlsf allocator does not target Windows, OSX or Android, skipping...\")\n   return()\n endif()\n "
        }
      ]
    },
    {
      "author": "Jackie Kay",
      "date": "2015-12-10T22:35:23Z",
      "sha": "f6f4e3ca2da0db7318106dbe3486c4be84a5c37b",
      "message": "Import tlsf allocator",
      "files_changed": 7,
      "additions": 1647,
      "deletions": 0,
      "commit_type": "code",
      "files": [
        {
          "sha": "ca45c283d01adb19eb0b8620fa9815ccd825fc5a",
          "filename": "tlsf/CMakeLists.txt",
          "status": "added",
          "additions": 35,
          "deletions": 0,
          "changes": 35,
          "blob_url": "https://github.com/ros2/tlsf/blob/f6f4e3ca2da0db7318106dbe3486c4be84a5c37b/tlsf%2FCMakeLists.txt",
          "raw_url": "https://github.com/ros2/tlsf/raw/f6f4e3ca2da0db7318106dbe3486c4be84a5c37b/tlsf%2FCMakeLists.txt",
          "contents_url": "https://api.github.com/repos/ros2/tlsf/contents/tlsf%2FCMakeLists.txt?ref=f6f4e3ca2da0db7318106dbe3486c4be84a5c37b",
          "patch": "@@ -0,0 +1,35 @@\n+cmake_minimum_required(VERSION 2.8.3)\n+\n+project(tlsf)\n+\n+find_package(ament_cmake REQUIRED)\n+\n+include_directories(include/tlsf)\n+add_library(${PROJECT_NAME} STATIC src/tlsf.c src/target.h include/tlsf/tlsf.h)\n+\n+set_target_properties(${PROJECT_NAME}\n+  PROPERTIES\n+    COMPILE_FLAGS \"-fvisibility=hidden -fvisibility-inlines-hidden\"\n+)\n+\n+ament_export_include_directories(include)\n+ament_export_libraries(${PROJECT_NAME})\n+\n+# Disable linting for now.\n+#if(AMENT_ENABLE_TESTING)\n+#  find_package(ament_lint_auto REQUIRED)\n+#  ament_lint_auto_find_test_dependencies()\n+#endif()\n+\n+ament_package()\n+\n+install(DIRECTORY include/\n+  DESTINATION include\n+)\n+\n+install(\n+  TARGETS ${PROJECT_NAME}\n+  ARCHIVE DESTINATION lib\n+  LIBRARY DESTINATION lib\n+  RUNTIME DESTINATION bin\n+)"
        },
        {
          "sha": "5f2dd7fca2ddaf423137d748d4818e2dba3f57fe",
          "filename": "tlsf/LICENSE",
          "status": "added",
          "additions": 505,
          "deletions": 0,
          "changes": 505,
          "blob_url": "https://github.com/ros2/tlsf/blob/f6f4e3ca2da0db7318106dbe3486c4be84a5c37b/tlsf%2FLICENSE",
          "raw_url": "https://github.com/ros2/tlsf/raw/f6f4e3ca2da0db7318106dbe3486c4be84a5c37b/tlsf%2FLICENSE",
          "contents_url": "https://api.github.com/repos/ros2/tlsf/contents/tlsf%2FLICENSE?ref=f6f4e3ca2da0db7318106dbe3486c4be84a5c37b",
          "patch": "@@ -0,0 +1,505 @@\n+                  GNU LESSER GENERAL PUBLIC LICENSE\n+                       Version 2.1, February 1999\n+\n+ Copyright (C) 1991, 1999 Free Software Foundation, Inc.\n+ 51 Franklin Street, Fifth Floor, Boston, MA  02110-1301  USA\n+ Everyone is permitted to copy and distribute verbatim copies\n+ of this license document, but changing it is not allowed.\n+\n+(This is the first released version of the Lesser GPL.  It also counts\n+ as the successor of the GNU Library Public License, version 2, hence\n+ the version number 2.1.)\n+\n+                            Preamble\n+\n+  The licenses for most software are designed to take away your\n+freedom to share and change it.  By contrast, the GNU General Public\n+Licenses are intended to guarantee your freedom to share and change\n+free software--to make sure the software is free for all its users.\n+\n+  This license, the Lesser General Public License, applies to some\n+specially designated software packages--typically libraries--of the\n+Free Software Foundation and other authors who decide to use it.  You\n+can use it too, but we suggest you first think carefully about whether\n+this license or the ordinary General Public License is the better\n+strategy to use in any particular case, based on the explanations below.\n+\n+  When we speak of free software, we are referring to freedom of use,\n+not price.  Our General Public Licenses are designed to make sure that\n+you have the freedom to distribute copies of free software (and charge\n+for this service if you wish); that you receive source code or can get\n+it if you want it; that you can change the software and use pieces of\n+it in new free programs; and that you are informed that you can do\n+these things.\n+\n+  To protect your rights, we need to make restrictions that forbid\n+distributors to deny you these rights or to ask you to surrender these\n+rights.  These restrictions translate to certain responsibilities for\n+you if you distribute copies of the library or if you modify it.\n+\n+  For example, if you distribute copies of the library, whether gratis\n+or for a fee, you must give the recipients all the rights that we gave\n+you.  You must make sure that they, too, receive or can get the source\n+code.  If you link other code with the library, you must provide\n+complete object files to the recipients, so that they can relink them\n+with the library after making changes to the library and recompiling\n+it.  And you must show them these terms so they know their rights.\n+\n+  We protect your rights with a two-step method: (1) we copyright the\n+library, and (2) we offer you this license, which gives you legal\n+permission to copy, distribute and/or modify the library.\n+\n+  To protect each distributor, we want to make it very clear that\n+there is no warranty for the free library.  Also, if the library is\n+modified by someone else and passed on, the recipients should know\n+that what they have is not the original version, so that the original\n+author's reputation will not be affected by problems that might be\n+introduced by others.\n+\n+  Finally, software patents pose a constant threat to the existence of\n+any free program.  We wish to make sure that a company cannot\n+effectively restrict the users of a free program by obtaining a\n+restrictive license from a patent holder.  Therefore, we insist that\n+any patent license obtained for a version of the library must be\n+consistent with the full freedom of use specified in this license.\n+\n+  Most GNU software, including some libraries, is covered by the\n+ordinary GNU General Public License.  This license, the GNU Lesser\n+General Public License, applies to certain designated libraries, and\n+is quite different from the ordinary General Public License.  We use\n+this license for certain libraries in order to permit linking those\n+libraries into non-free programs.\n+\n+  When a program is linked with a library, whether statically or using\n+a shared library, the combination of the two is legally speaking a\n+combined work, a derivative of the original library.  The ordinary\n+General Public License therefore permits such linking only if the\n+entire combination fits its criteria of freedom.  The Lesser General\n+Public License permits more lax criteria for linking other code with\n+the library.\n+\n+  We call this license the \"Lesser\" General Public License because it\n+does Less to protect the user's freedom than the ordinary General\n+Public License.  It also provides other free software developers Less\n+of an advantage over competing non-free programs.  These disadvantages\n+are the reason we use the ordinary General Public License for many\n+libraries.  However, the Lesser license provides advantages in certain\n+special circumstances.\n+\n+  For example, on rare occasions, there may be a special need to\n+encourage the widest possible use of a certain library, so that it becomes\n+a de-facto standard.  To achieve this, non-free programs must be\n+allowed to use the library.  A more frequent case is that a free\n+library does the same job as widely used non-free libraries.  In this\n+case, there is little to gain by limiting the free library to free\n+software only, so we use the Lesser General Public License.\n+\n+  In other cases, permission to use a particular library in non-free\n+programs enables a greater number of people to use a large body of\n+free software.  For example, permission to use the GNU C Library in\n+non-free programs enables many more people to use the whole GNU\n+operating system, as well as its variant, the GNU/Linux operating\n+system.\n+\n+  Although the Lesser General Public License is Less protective of the\n+users' freedom, it does ensure that the user of a program that is\n+linked with the Library has the freedom and the wherewithal to run\n+that program using a modified version of the Library.\n+\n+  The precise terms and conditions for copying, distribution and\n+modification follow.  Pay close attention to the difference between a\n+\"work based on the library\" and a \"work that uses the library\".  The\n+former contains code derived from the library, whereas the latter must\n+be combined with the library in order to run.\n+\n+                  GNU LESSER GENERAL PUBLIC LICENSE\n+   TERMS AND CONDITIONS FOR COPYING, DISTRIBUTION AND MODIFICATION\n+\n+  0. This License Agreement applies to any software library or other\n+program which contains a notice placed by the copyright holder or\n+other authorized party saying it may be distributed under the terms of\n+this Lesser General Public License (also called \"this License\").\n+Each licensee is addressed as \"you\".\n+\n+  A \"library\" means a collection of software functions and/or data\n+prepared so as to be conveniently linked with application programs\n+(which use some of those functions and data) to form executables.\n+\n+  The \"Library\", below, refers to any such software library or work\n+which has been distributed under these terms.  A \"work based on the\n+Library\" means either the Library or any derivative work under\n+copyright law: that is to say, a work containing the Library or a\n+portion of it, either verbatim or with modifications and/or translated\n+straightforwardly into another language.  (Hereinafter, translation is\n+included without limitation in the term \"modification\".)\n+\n+  \"Source code\" for a work means the preferred form of the work for\n+making modifications to it.  For a library, complete source code means\n+all the source code for all modules it contains, plus any associated\n+interface definition files, plus the scripts used to control compilation\n+and installation of the library.\n+\n+  Activities other than copying, distribution and modification are not\n+covered by this License; they are outside its scope.  The act of\n+running a program using the Library is not restricted, and output from\n+such a program is covered only if its contents constitute a work based\n+on the Library (independent of the use of the Library in a tool for\n+writing it).  Whether that is true depends on what the Library does\n+and what the program that uses the Library does.\n+\n+  1. You may copy and distribute verbatim copies of the Library's\n+complete source code as you receive it, in any medium, provided that\n+you conspicuously and appropriately publish on each copy an\n+appropriate copyright notice and disclaimer of warranty; keep intact\n+all the notices that refer to this License and to the absence of any\n+warranty; and distribute a copy of this License along with the\n+Library.\n+\n+  You may charge a fee for the physical act of transferring a copy,\n+and you may at your option offer warranty protection in exchange for a\n+fee.\n+\n+  2. You may modify your copy or copies of the Library or any portion\n+of it, thus forming a work based on the Library, and copy and\n+distribute such modifications or work under the terms of Section 1\n+above, provided that you also meet all of these conditions:\n+\n+    a) The modified work must itself be a software library.\n+\n+    b) You must cause the files modified to carry prominent notices\n+    stating that you changed the files and the date of any change.\n+\n+    c) You must cause the whole of the work to be licensed at no\n+    charge to all third parties under the terms of this License.\n+\n+    d) If a facility in the modified Library refers to a function or a\n+    table of data to be supplied by an application program that uses\n+    the facility, other than as an argument passed when the facility\n+    is invoked, then you must make a good faith effort to ensure that,\n+    in the event an application does not supply such function or\n+    table, the facility still operates, and performs whatever part of\n+    its purpose remains meaningful.\n+\n+    (For example, a function in a library to compute square roots has\n+    a purpose that is entirely well-defined independent of the\n+    application.  Therefore, Subsection 2d requires that any\n+    application-supplied function or table used by this function must\n+    be optional: if the application does not supply it, the square\n+    root function must still compute square roots.)\n+\n+These requirements apply to the modified work as a whole.  If\n+identifiable sections of that work are not derived from the Library,\n+and can be reasonably considered independent and separate works in\n+themselves, then this License, and its terms, do not apply to those\n+sections when you distribute them as separate works.  But when you\n+distribute the same sections as part of a whole which is a work based\n+on the Library, the distribution of the whole must be on the terms of\n+this License, whose permissions for other licensees extend to the\n+entire whole, and thus to each and every part regardless of who wrote\n+it.\n+\n+Thus, it is not the intent of this section to claim rights or contest\n+your rights to work written entirely by you; rather, the intent is to\n+exercise the right to control the distribution of derivative or\n+collective works based on the Library.\n+\n+In addition, mere aggregation of another work not based on the Library\n+with the Library (or with a work based on the Library) on a volume of\n+a storage or distribution medium does not bring the other work under\n+the scope of this License.\n+\n+  3. You may opt to apply the terms of the ordinary GNU General Public\n+License instead of this License to a given copy of the Library.  To do\n+this, you must alter all the notices that refer to this License, so\n+that they refer to the ordinary GNU General Public License, version 2,\n+instead of to this License.  (If a newer version than version 2 of the\n+ordinary GNU General Public License has appeared, then you can specify\n+that version instead if you wish.)  Do not make any other change in\n+these notices.\n+\n+  Once this change is made in a given copy, it is irreversible for\n+that copy, so the ordinary GNU General Public License applies to all\n+subsequent copies and derivative works made from that copy.\n+\n+  This option is useful when you wish to copy part of the code of\n+the Library into a program that is not a library.\n+\n+  4. You may copy and distribute the Library (or a portion or\n+derivative of it, under Section 2) in object code or executable form\n+under the terms of Sections 1 and 2 above provided that you accompany\n+it with the complete corresponding machine-readable source code, which\n+must be distributed under the terms of Sections 1 and 2 above on a\n+medium customarily used for software interchange.\n+\n+  If distribution of object code is made by offering access to copy\n+from a designated place, then offering equivalent access to copy the\n+source code from the same place satisfies the requirement to\n+distribute the source code, even though third parties are not\n+compelled to copy the source along with the object code.\n+\n+  5. A program that contains no derivative of any portion of the\n+Library, but is designed to work with the Library by being compiled or\n+linked with it, is called a \"work that uses the Library\".  Such a\n+work, in isolation, is not a derivative work of the Library, and\n+therefore falls outside the scope of this License.\n+\n+  However, linking a \"work that uses the Library\" with the Library\n+creates an executable that is a derivative of the Library (because it\n+contains portions of the Library), rather than a \"work that uses the\n+library\".  The executable is therefore covered by this License.\n+Section 6 states terms for distribution of such executables.\n+\n+  When a \"work that uses the Library\" uses material from a header file\n+that is part of the Library, the object code for the work may be a\n+derivative work of the Library even though the source code is not.\n+Whether this is true is especially significant if the work can be\n+linked without the Library, or if the work is itself a library.  The\n+threshold for this to be true is not precisely defined by law.\n+\n+  If such an object file uses only numerical parameters, data\n+structure layouts and accessors, and small macros and small inline\n+functions (ten lines or less in length), then the use of the object\n+file is unrestricted, regardless of whether it is legally a derivative\n+work.  (Executables containing this object code plus portions of the\n+Library will still fall under Section 6.)\n+\n+  Otherwise, if the work is a derivative of the Library, you may\n+distribute the object code for the work under the terms of Section 6.\n+Any executables containing that work also fall under Section 6,\n+whether or not they are linked directly with the Library itself.\n+\n+  6. As an exception to the Sections above, you may also combine or\n+link a \"work that uses the Library\" with the Library to produce a\n+work containing portions of the Library, and distribute that work\n+under terms of your choice, provided that the terms permit\n+modification of the work for the customer's own use and reverse\n+engineering for debugging such modifications.\n+\n+  You must give prominent notice with each copy of the work that the\n+Library is used in it and that the Library and its use are covered by\n+this License.  You must supply a copy of this License.  If the work\n+during execution displays copyright notices, you must include the\n+copyright notice for the Library among them, as well as a reference\n+directing the user to the copy of this License.  Also, you must do one\n+of these things:\n+\n+    a) Accompany the work with the complete corresponding\n+    machine-readable source code for the Library including whatever\n+    changes were used in the work (which must be distributed under\n+    Sections 1 and 2 above); and, if the work is an executable linked\n+    with the Library, with the complete machine-readable \"work that\n+    uses the Library\", as object code and/or source code, so that the\n+    user can modify the Library and then relink to produce a modified\n+    executable containing the modified Library.  (It is understood\n+    that the user who changes the contents of definitions files in the\n+    Library will not necessarily be able to recompile the application\n+    to use the modified definitions.)\n+\n+    b) Use a suitable shared library mechanism for linking with the\n+    Library.  A suitable mechanism is one that (1) uses at run time a\n+    copy of the library already present on the user's computer system,\n+    rather than copying library functions into the executable, and (2)\n+    will operate properly with a modified version of the library, if\n+    the user installs one, as long as the modified version is\n+    interface-compatible with the version that the work was made with.\n+\n+    c) Accompany the work with a written offer, valid for at\n+    least three years, to give the same user the materials\n+    specified in Subsection 6a, above, for a charge no more\n+    than the cost of performing this distribution.\n+\n+    d) If distribution of the work is made by offering access to copy\n+    from a designated place, offer equivalent access to copy the above\n+    specified materials from the same place.\n+\n+    e) Verify that the user has already received a copy of these\n+    materials or that you have already sent this user a copy.\n+\n+  For an executable, the required form of the \"work that uses the\n+Library\" must include any data and utility programs needed for\n+reproducing the executable from it.  However, as a special exception,\n+the materials to be distributed need not include anything that is\n+normally distributed (in either source or binary form) with the major\n+components (compiler, kernel, and so on) of the operating system on\n+which the executable runs, unless that component itself accompanies\n+the executable.\n+\n+  It may happen that this requirement contradicts the license\n+restrictions of other proprietary libraries that do not normally\n+accompany the operating system.  Such a contradiction means you cannot\n+use both them and the Library together in an executable that you\n+distribute.\n+\n+  7. You may place library facilities that are a work based on the\n+Library side-by-side in a single library together with other library\n+facilities not covered by this License, and distribute such a combined\n+library, provided that the separate distribution of the work based on\n+the Library and of the other library facilities is otherwise\n+permitted, and provided that you do these two things:\n+\n+    a) Accompany the combined library with a copy of the same work\n+    based on the Library, uncombined with any other library\n+    facilities.  This must be distributed under the terms of the\n+    Sections above.\n+\n+    b) Give prominent notice with the combined library of the fact\n+    that part of it is a work based on the Library, and explaining\n+    where to find the accompanying uncombined form of the same work.\n+\n+  8. You may not copy, modify, sublicense, link with, or distribute\n+the Library except as expressly provided under this License.  Any\n+attempt otherwise to copy, modify, sublicense, link with, or\n+distribute the Library is void, and will automatically terminate your\n+rights under this License.  However, parties who have received copies,\n+or rights, from you under this License will not have their licenses\n+terminated so long as such parties remain in full compliance.\n+\n+  9. You are not required to accept this License, since you have not\n+signed it.  However, nothing else grants you permission to modify or\n+distribute the Library or its derivative works.  These actions are\n+prohibited by law if you do not accept this License.  Therefore, by\n+modifying or distributing the Library (or any work based on the\n+Library), you indicate your acceptance of this License to do so, and\n+all its terms and conditions for copying, distributing or modifying\n+the Library or works based on it.\n+\n+  10. Each time you redistribute the Library (or any work based on the\n+Library), the recipient automatically receives a license from the\n+original licensor to copy, distribute, link with or modify the Library\n+subject to these terms and conditions.  You may not impose any further\n+restrictions on the recipients' exercise of the rights granted herein.\n+You are not responsible for enforcing compliance by third parties with\n+this License.\n+\n+  11. If, as a consequence of a court judgment or allegation of patent\n+infringement or for any other reason (not limited to patent issues),\n+conditions are imposed on you (whether by court order, agreement or\n+otherwise) that contradict the conditions of this License, they do not\n+excuse you from the conditions of this License.  If you cannot\n+distribute so as to satisfy simultaneously your obligations under this\n+License and any other pertinent obligations, then as a consequence you\n+may not distribute the Library at all.  For example, if a patent\n+license would not permit royalty-free redistribution of the Library by\n+all those who receive copies directly or indirectly through you, then\n+the only way you could satisfy both it and this License would be to\n+refrain entirely from distribution of the Library.\n+\n+If any portion of this section is held invalid or unenforceable under any\n+particular circumstance, the balance of the section is intended to apply,\n+and the section as a whole is intended to apply in other circumstances.\n+\n+It is not the purpose of this section to induce you to infringe any\n+patents or other property right claims or to contest validity of any\n+such claims; this section has the sole purpose of protecting the\n+integrity of the free software distribution system which is\n+implemented by public license practices.  Many people have made\n+generous contributions to the wide range of software distributed\n+through that system in reliance on consistent application of that\n+system; it is up to the author/donor to decide if he or she is willing\n+to distribute software through any other system and a licensee cannot\n+impose that choice.\n+\n+This section is intended to make thoroughly clear what is believed to\n+be a consequence of the rest of this License.\n+\n+  12. If the distribution and/or use of the Library is restricted in\n+certain countries either by patents or by copyrighted interfaces, the\n+original copyright holder who places the Library under this License may add\n+an explicit geographical distribution limitation excluding those countries,\n+so that distribution is permitted only in or among countries not thus\n+excluded.  In such case, this License incorporates the limitation as if\n+written in the body of this License.\n+\n+  13. The Free Software Foundation may publish revised and/or new\n+versions of the Lesser General Public License from time to time.\n+Such new versions will be similar in spirit to the present version,\n+but may differ in detail to address new problems or concerns.\n+\n+Each version is given a distinguishing version number.  If the Library\n+specifies a version number of this License which applies to it and\n+\"any later version\", you have the option of following the terms and\n+conditions either of that version or of any later version published by\n+the Free Software Foundation.  If the Library does not specify a\n+license version number, you may choose any version ever published by\n+the Free Software Foundation.\n+\n+  14. If you wish to incorporate parts of the Library into other free\n+programs whose distribution conditions are incompatible with these,\n+write to the author to ask for permission.  For software which is\n+copyrighted by the Free Software Foundation, write to the Free\n+Software Foundation; we sometimes make exceptions for this.  Our\n+decision will be guided by the two goals of preserving the free status\n+of all derivatives of our free software and of promoting the sharing\n+and reuse of software generally.\n+\n+                            NO WARRANTY\n+\n+  15. BECAUSE THE LIBRARY IS LICENSED FREE OF CHARGE, THERE IS NO\n+WARRANTY FOR THE LIBRARY, TO THE EXTENT PERMITTED BY APPLICABLE LAW.\n+EXCEPT WHEN OTHERWISE STATED IN WRITING THE COPYRIGHT HOLDERS AND/OR\n+OTHER PARTIES PROVIDE THE LIBRARY \"AS IS\" WITHOUT WARRANTY OF ANY\n+KIND, EITHER EXPRESSED OR IMPLIED, INCLUDING, BUT NOT LIMITED TO, THE\n+IMPLIED WARRANTIES OF MERCHANTABILITY AND FITNESS FOR A PARTICULAR\n+PURPOSE.  THE ENTIRE RISK AS TO THE QUALITY AND PERFORMANCE OF THE\n+LIBRARY IS WITH YOU.  SHOULD THE LIBRARY PROVE DEFECTIVE, YOU ASSUME\n+THE COST OF ALL NECESSARY SERVICING, REPAIR OR CORRECTION.\n+\n+  16. IN NO EVENT UNLESS REQUIRED BY APPLICABLE LAW OR AGREED TO IN\n+WRITING WILL ANY COPYRIGHT HOLDER, OR ANY OTHER PARTY WHO MAY MODIFY\n+AND/OR REDISTRIBUTE THE LIBRARY AS PERMITTED ABOVE, BE LIABLE TO YOU\n+FOR DAMAGES, INCLUDING ANY GENERAL, SPECIAL, INCIDENTAL OR\n+CONSEQUENTIAL DAMAGES ARISING OUT OF THE USE OR INABILITY TO USE THE\n+LIBRARY (INCLUDING BUT NOT LIMITED TO LOSS OF DATA OR DATA BEING\n+RENDERED INACCURATE OR LOSSES SUSTAINED BY YOU OR THIRD PARTIES OR A\n+FAILURE OF THE LIBRARY TO OPERATE WITH ANY OTHER SOFTWARE), EVEN IF\n+SUCH HOLDER OR OTHER PARTY HAS BEEN ADVISED OF THE POSSIBILITY OF SUCH\n+DAMAGES.\n+\n+                     END OF TERMS AND CONDITIONS\n+\n+           How to Apply These Terms to Your New Libraries\n+\n+  If you develop a new library, and you want it to be of the greatest\n+possible use to the public, we recommend making it free software that\n+everyone can redistribute and change.  You can do so by permitting\n+redistribution under these terms (or, alternatively, under the terms of the\n+ordinary General Public License).\n+\n+  To apply these terms, attach the following notices to the library.  It is\n+safest to attach them to the start of each source file to most effectively\n+convey the exclusion of warranty; and each file should have at least the\n+\"copyright\" line and a pointer to where the full notice is found.\n+\n+    {description}\n+    Copyright (C) {year} {fullname}\n+\n+    This library is free software; you can redistribute it and/or\n+    modify it under the terms of the GNU Lesser General Public\n+    License as published by the Free Software Foundation; either\n+    version 2.1 of the License, or (at your option) any later version.\n+\n+    This library is distributed in the hope that it will be useful,\n+    but WITHOUT ANY WARRANTY; without even the implied warranty of\n+    MERCHANTABILITY or FITNESS FOR A PARTICULAR PURPOSE.  See the GNU\n+    Lesser General Public License for more details.\n+\n+    You should have received a copy of the GNU Lesser General Public\n+    License along with this library; if not, write to the Free Software\n+    Foundation, Inc., 51 Franklin Street, Fifth Floor, Boston, MA  02110-1301\n+    USA\n+\n+Also add information on how to contact you by electronic and paper mail.\n+\n+You should also get your employer (if you work as a programmer) or your\n+school, if any, to sign a \"copyright disclaimer\" for the library, if\n+necessary.  Here is a sample; alter the names:\n+\n+  Yoyodyne, Inc., hereby disclaims all copyright interest in the\n+  library `Frob' (a library for tweaking knobs) written by James Random\n+  Hacker.\n+\n+  {signature of Ty Coon}, 1 April 1990\n+  Ty Coon, President of Vice\n+\n+That's all there is to it!\n+"
        },
        {
          "sha": "e510ac5b55820dcb489080657519e93c1c1e565b",
          "filename": "tlsf/README.md",
          "status": "added",
          "additions": 3,
          "deletions": 0,
          "changes": 3,
          "blob_url": "https://github.com/ros2/tlsf/blob/f6f4e3ca2da0db7318106dbe3486c4be84a5c37b/tlsf%2FREADME.md",
          "raw_url": "https://github.com/ros2/tlsf/raw/f6f4e3ca2da0db7318106dbe3486c4be84a5c37b/tlsf%2FREADME.md",
          "contents_url": "https://api.github.com/repos/ros2/tlsf/contents/tlsf%2FREADME.md?ref=f6f4e3ca2da0db7318106dbe3486c4be84a5c37b",
          "patch": "@@ -0,0 +1,3 @@\n+This package contains a snapshot of TLSF version 2.4.6 downloaded as a .tar from: http://www.gii.upv.es/tlsf/main/repo\n+\n+Github repository: https://github.com/emeryberger/Malloc-Implementations/tree/master/allocators/TLSF/TLSF-2.4.6"
        },
        {
          "sha": "88b015edbefefd913b5630a3ffc871b4ad928512",
          "filename": "tlsf/include/tlsf/tlsf.h",
          "status": "added",
          "additions": 48,
          "deletions": 0,
          "changes": 48,
          "blob_url": "https://github.com/ros2/tlsf/blob/f6f4e3ca2da0db7318106dbe3486c4be84a5c37b/tlsf%2Finclude%2Ftlsf%2Ftlsf.h",
          "raw_url": "https://github.com/ros2/tlsf/raw/f6f4e3ca2da0db7318106dbe3486c4be84a5c37b/tlsf%2Finclude%2Ftlsf%2Ftlsf.h",
          "contents_url": "https://api.github.com/repos/ros2/tlsf/contents/tlsf%2Finclude%2Ftlsf%2Ftlsf.h?ref=f6f4e3ca2da0db7318106dbe3486c4be84a5c37b",
          "patch": "@@ -0,0 +1,48 @@\n+/*\n+ * Two Levels Segregate Fit memory allocator (TLSF)\n+ * Version 2.4.6\n+ *\n+ * Written by Miguel Masmano Tello <mimastel@doctor.upv.es>\n+ *\n+ * Thanks to Ismael Ripoll for his suggestions and reviews\n+ *\n+ * Copyright (C) 2008, 2007, 2006, 2005, 2004\n+ *\n+ * This code is released using a dual license strategy: GPL/LGPL\n+ * You can choose the licence that better fits your requirements.\n+ *\n+ * Released under the terms of the GNU General Public License Version 2.0\n+ * Released under the terms of the GNU Lesser General Public License Version 2.1\n+ *\n+ */\n+\n+#ifdef __cplusplus\n+extern \"C\"\n+{\n+#endif\n+\n+#ifndef _TLSF_H_\n+#define _TLSF_H_\n+\n+#include <sys/types.h>\n+\n+extern size_t init_memory_pool(size_t, void *);\n+extern size_t get_used_size(void *);\n+extern size_t get_max_size(void *);\n+extern void destroy_memory_pool(void *);\n+extern size_t add_new_area(void *, size_t, void *);\n+extern void *malloc_ex(size_t, void *);\n+extern void free_ex(void *, void *);\n+extern void *realloc_ex(void *, size_t, void *);\n+extern void *calloc_ex(size_t, size_t, void *);\n+\n+extern void *tlsf_malloc(size_t size);\n+extern void tlsf_free(void *ptr);\n+extern void *tlsf_realloc(void *ptr, size_t size);\n+extern void *tlsf_calloc(size_t nelem, size_t elem_size);\n+\n+#endif\n+\n+#ifdef __cplusplus\n+}\n+#endif"
        },
        {
          "sha": "43a6a6101404e9cf6b518199bd660291a232789e",
          "filename": "tlsf/package.xml",
          "status": "added",
          "additions": 20,
          "deletions": 0,
          "changes": 20,
          "blob_url": "https://github.com/ros2/tlsf/blob/f6f4e3ca2da0db7318106dbe3486c4be84a5c37b/tlsf%2Fpackage.xml",
          "raw_url": "https://github.com/ros2/tlsf/raw/f6f4e3ca2da0db7318106dbe3486c4be84a5c37b/tlsf%2Fpackage.xml",
          "contents_url": "https://api.github.com/repos/ros2/tlsf/contents/tlsf%2Fpackage.xml?ref=f6f4e3ca2da0db7318106dbe3486c4be84a5c37b",
          "patch": "@@ -0,0 +1,20 @@\n+<?xml version=\"1.0\"?>\n+<package format=\"2\">\n+  <name>tlsf</name>\n+  <version>0.0.0</version>\n+  <description>TLSF allocator version 2.4.6</description>\n+  <maintainer email=\"jackie@osrfoundation.org\">Jackie Kay</maintainer>\n+  <license>GNU Lesser Public License 2.1</license>\n+\n+  <buildtool_depend>ament_cmake</buildtool_depend>\n+\n+  <build_depend>ament_cmake</build_depend>\n+  <exec_depend>ament_cmake</exec_depend>\n+\n+  <test_depend>ament_lint_auto</test_depend>\n+  <test_depend>ament_lint_common</test_depend>\n+\n+  <export>\n+    <build_type>ament_cmake</build_type>\n+  </export>\n+</package>"
        },
        {
          "sha": "1afd62aef20978e7fb998d11be68266fb834f062",
          "filename": "tlsf/src/target.h",
          "status": "added",
          "additions": 12,
          "deletions": 0,
          "changes": 12,
          "blob_url": "https://github.com/ros2/tlsf/blob/f6f4e3ca2da0db7318106dbe3486c4be84a5c37b/tlsf%2Fsrc%2Ftarget.h",
          "raw_url": "https://github.com/ros2/tlsf/raw/f6f4e3ca2da0db7318106dbe3486c4be84a5c37b/tlsf%2Fsrc%2Ftarget.h",
          "contents_url": "https://api.github.com/repos/ros2/tlsf/contents/tlsf%2Fsrc%2Ftarget.h?ref=f6f4e3ca2da0db7318106dbe3486c4be84a5c37b",
          "patch": "@@ -0,0 +1,12 @@\n+#ifndef _TARGET_H_\n+#define _TARGET_H_\n+\n+#include <pthread.h>\n+\n+#define TLSF_MLOCK_T            pthread_mutex_t\n+#define TLSF_CREATE_LOCK(l)     pthread_mutex_init (l, NULL)\n+#define TLSF_DESTROY_LOCK(l)    pthread_mutex_destroy(l)\n+#define TLSF_ACQUIRE_LOCK(l)    pthread_mutex_lock(l)\n+#define TLSF_RELEASE_LOCK(l)    pthread_mutex_unlock(l)\n+\n+#endif"
        },
        {
          "sha": "b71a99d7ba8213d42caf3c33d9d9dbbdfa8de0b9",
          "filename": "tlsf/src/tlsf.c",
          "status": "added",
          "additions": 1024,
          "deletions": 0,
          "changes": 1024,
          "blob_url": "https://github.com/ros2/tlsf/blob/f6f4e3ca2da0db7318106dbe3486c4be84a5c37b/tlsf%2Fsrc%2Ftlsf.c",
          "raw_url": "https://github.com/ros2/tlsf/raw/f6f4e3ca2da0db7318106dbe3486c4be84a5c37b/tlsf%2Fsrc%2Ftlsf.c",
          "contents_url": "https://api.github.com/repos/ros2/tlsf/contents/tlsf%2Fsrc%2Ftlsf.c?ref=f6f4e3ca2da0db7318106dbe3486c4be84a5c37b",
          "patch": "@@ -0,0 +1,1024 @@\n+/* \n+ * Two Levels Segregate Fit memory allocator (TLSF)\n+ * Version 2.4.6\n+ *\n+ * Written by Miguel Masmano Tello <mimastel@doctor.upv.es>\n+ *\n+ * Thanks to Ismael Ripoll for his suggestions and reviews\n+ *\n+ * Copyright (C) 2008, 2007, 2006, 2005, 2004\n+ *\n+ * This code is released using a dual license strategy: GPL/LGPL\n+ * You can choose the licence that better fits your requirements.\n+ *\n+ * Released under the terms of the GNU General Public License Version 2.0\n+ * Released under the terms of the GNU Lesser General Public License Version 2.1\n+ *\n+ */\n+\n+/*\n+ * Code contributions:\n+ *\n+ * (Jul 28 2007)  Herman ten Brugge <hermantenbrugge@home.nl>:\n+ *\n+ * - Add 64 bit support. It now runs on x86_64 and solaris64.\n+ * - I also tested this on vxworks/32and solaris/32 and i386/32 processors.\n+ * - Remove assembly code. I could not measure any performance difference \n+ *   on my core2 processor. This also makes the code more portable.\n+ * - Moved defines/typedefs from tlsf.h to tlsf.c\n+ * - Changed MIN_BLOCK_SIZE to sizeof (free_ptr_t) and BHDR_OVERHEAD to \n+ *   (sizeof (bhdr_t) - MIN_BLOCK_SIZE). This does not change the fact \n+ *    that the minumum size is still sizeof \n+ *   (bhdr_t).\n+ * - Changed all C++ comment style to C style. (// -> /.* ... *./)\n+ * - Used ls_bit instead of ffs and ms_bit instead of fls. I did this to \n+ *   avoid confusion with the standard ffs function which returns \n+ *   different values.\n+ * - Created set_bit/clear_bit fuctions because they are not present \n+ *   on x86_64.\n+ * - Added locking support + extra file target.h to show how to use it.\n+ * - Added get_used_size function (REMOVED in 2.4)\n+ * - Added rtl_realloc and rtl_calloc function\n+ * - Implemented realloc clever support.\n+ * - Added some test code in the example directory.\n+ * - Bug fixed (discovered by the rockbox project: www.rockbox.org).       \n+ *\n+ * (Oct 23 2006) Adam Scislowicz: \n+ *\n+ * - Support for ARMv5 implemented\n+ *\n+ */\n+\n+/*#define USE_SBRK        (0) */\n+/*#define USE_MMAP        (0) */\n+\n+#ifdef __cplusplus\n+extern \"C\"\n+{\n+#endif\n+\n+#ifndef USE_PRINTF\n+#define USE_PRINTF      (1)\n+#endif\n+\n+#include <string.h>\n+\n+#ifndef TLSF_USE_LOCKS\n+#define\tTLSF_USE_LOCKS \t(0)\n+#endif\n+\n+#ifndef TLSF_STATISTIC\n+#define\tTLSF_STATISTIC \t(0)\n+#endif\n+\n+#ifndef USE_MMAP\n+#define\tUSE_MMAP \t(0)\n+#endif\n+\n+#ifndef USE_SBRK\n+#define\tUSE_SBRK \t(0)\n+#endif\n+\n+\n+#if TLSF_USE_LOCKS\n+#include \"target.h\"\n+#else\n+#define TLSF_CREATE_LOCK(_unused_)   do{}while(0)\n+#define TLSF_DESTROY_LOCK(_unused_)  do{}while(0) \n+#define TLSF_ACQUIRE_LOCK(_unused_)  do{}while(0)\n+#define TLSF_RELEASE_LOCK(_unused_)  do{}while(0)\n+#endif\n+\n+#if TLSF_STATISTIC\n+#define\tTLSF_ADD_SIZE(tlsf, b) do {\t\t\t\t\t\t\t\t\t\\\n+\t\ttlsf->used_size += (b->size & BLOCK_SIZE) + BHDR_OVERHEAD;\t\\\n+\t\tif (tlsf->used_size > tlsf->max_size) \t\t\t\t\t\t\\\n+\t\t\ttlsf->max_size = tlsf->used_size;\t\t\t\t\t\t\\\n+\t\t} while(0)\n+\n+#define\tTLSF_REMOVE_SIZE(tlsf, b) do {\t\t\t\t\t\t\t\t\\\n+\t\ttlsf->used_size -= (b->size & BLOCK_SIZE) + BHDR_OVERHEAD;\t\\\n+\t} while(0)\n+#else\n+#define\tTLSF_ADD_SIZE(tlsf, b)\t     do{}while(0)\n+#define\tTLSF_REMOVE_SIZE(tlsf, b)    do{}while(0)\n+#endif\n+\n+#if USE_MMAP || USE_SBRK\n+#include <unistd.h>\n+#endif\n+\n+#if USE_MMAP\n+#include <sys/mman.h>\n+#endif\n+\n+#include \"tlsf.h\"\n+\n+#if !defined(__GNUC__)\n+#ifndef __inline__\n+#define __inline__\n+#endif\n+#endif\n+\n+/* The  debug functions  only can  be used  when _DEBUG_TLSF_  is set. */\n+#ifndef _DEBUG_TLSF_\n+#define _DEBUG_TLSF_  (0)\n+#endif\n+\n+/*************************************************************************/\n+/* Definition of the structures used by TLSF */\n+\n+\n+/* Some IMPORTANT TLSF parameters */\n+/* Unlike the preview TLSF versions, now they are statics */\n+#define BLOCK_ALIGN (sizeof(void *) * 2)\n+\n+#define MAX_FLI\t\t(30)\n+#define MAX_LOG2_SLI\t(5)\n+#define MAX_SLI\t\t(1 << MAX_LOG2_SLI)     /* MAX_SLI = 2^MAX_LOG2_SLI */\n+\n+#define FLI_OFFSET\t(6)     /* tlsf structure just will manage blocks bigger */\n+/* than 128 bytes */\n+#define SMALL_BLOCK\t(128)\n+#define REAL_FLI\t(MAX_FLI - FLI_OFFSET)\n+#define MIN_BLOCK_SIZE\t(sizeof (free_ptr_t))\n+#define BHDR_OVERHEAD\t(sizeof (bhdr_t) - MIN_BLOCK_SIZE)\n+#define TLSF_SIGNATURE\t(0x2A59FA59)\n+\n+#define\tPTR_MASK\t(sizeof(void *) - 1)\n+#define BLOCK_SIZE\t(0xFFFFFFFF - PTR_MASK)\n+\n+#define GET_NEXT_BLOCK(_addr, _r) ((bhdr_t *) ((char *) (_addr) + (_r)))\n+#define\tMEM_ALIGN\t\t  ((BLOCK_ALIGN) - 1)\n+#define ROUNDUP_SIZE(_r)          (((_r) + MEM_ALIGN) & ~MEM_ALIGN)\n+#define ROUNDDOWN_SIZE(_r)        ((_r) & ~MEM_ALIGN)\n+#define ROUNDUP(_x, _v)           ((((~(_x)) + 1) & ((_v)-1)) + (_x))\n+\n+#define BLOCK_STATE\t(0x1)\n+#define PREV_STATE\t(0x2)\n+\n+/* bit 0 of the block size */\n+#define FREE_BLOCK\t(0x1)\n+#define USED_BLOCK\t(0x0)\n+\n+/* bit 1 of the block size */\n+#define PREV_FREE\t(0x2)\n+#define PREV_USED\t(0x0)\n+\n+\n+#define DEFAULT_AREA_SIZE (1024*10)\n+\n+#ifdef USE_MMAP\n+#define PAGE_SIZE (getpagesize())\n+#endif\n+\n+#ifdef USE_PRINTF\n+#include <stdio.h>\n+# define PRINT_MSG(fmt, args...) printf(fmt, ## args)\n+# define ERROR_MSG(fmt, args...) printf(fmt, ## args)\n+#else\n+# if !defined(PRINT_MSG)\n+#  define PRINT_MSG(fmt, args...)\n+# endif\n+# if !defined(ERROR_MSG)\n+#  define ERROR_MSG(fmt, args...)\n+# endif\n+#endif\n+\n+typedef unsigned int u32_t;     /* NOTE: Make sure that this type is 4 bytes long on your computer */\n+typedef unsigned char u8_t;     /* NOTE: Make sure that this type is 1 byte on your computer */\n+\n+typedef struct free_ptr_struct {\n+    struct bhdr_struct *prev;\n+    struct bhdr_struct *next;\n+} free_ptr_t;\n+\n+typedef struct bhdr_struct {\n+    /* This pointer is just valid if the first bit of size is set */\n+    struct bhdr_struct *prev_hdr;\n+    /* The size is stored in bytes */\n+    size_t size;                /* bit 0 indicates whether the block is used and */\n+    /* bit 1 allows to know whether the previous block is free */\n+    union {\n+        struct free_ptr_struct free_ptr;\n+        u8_t buffer[1];         /*sizeof(struct free_ptr_struct)]; */\n+    } ptr;\n+} bhdr_t;\n+\n+/* This structure is embedded at the beginning of each area, giving us\n+ * enough information to cope with a set of areas */\n+\n+typedef struct area_info_struct {\n+    bhdr_t *end;\n+    struct area_info_struct *next;\n+} area_info_t;\n+\n+typedef struct TLSF_struct {\n+    /* the TLSF's structure signature */\n+    u32_t tlsf_signature;\n+\n+#if TLSF_USE_LOCKS\n+    TLSF_MLOCK_T lock;\n+#endif\n+\n+#if TLSF_STATISTIC\n+    /* These can not be calculated outside tlsf because we\n+     * do not know the sizes when freeing/reallocing memory. */\n+    size_t used_size;\n+    size_t max_size;\n+#endif\n+\n+    /* A linked list holding all the existing areas */\n+    area_info_t *area_head;\n+\n+    /* the first-level bitmap */\n+    /* This array should have a size of REAL_FLI bits */\n+    u32_t fl_bitmap;\n+\n+    /* the second-level bitmap */\n+    u32_t sl_bitmap[REAL_FLI];\n+\n+    bhdr_t *matrix[REAL_FLI][MAX_SLI];\n+} tlsf_t;\n+\n+\n+/******************************************************************/\n+/**************     Helping functions    **************************/\n+/******************************************************************/\n+static __inline__ void set_bit(int nr, u32_t * addr);\n+static __inline__ void clear_bit(int nr, u32_t * addr);\n+static __inline__ int ls_bit(int x);\n+static __inline__ int ms_bit(int x);\n+static __inline__ void MAPPING_SEARCH(size_t * _r, int *_fl, int *_sl);\n+static __inline__ void MAPPING_INSERT(size_t _r, int *_fl, int *_sl);\n+static __inline__ bhdr_t *FIND_SUITABLE_BLOCK(tlsf_t * _tlsf, int *_fl, int *_sl);\n+static __inline__ bhdr_t *process_area(void *area, size_t size);\n+#if USE_SBRK || USE_MMAP\n+static __inline__ void *get_new_area(size_t * size);\n+#endif\n+\n+static const int table[] = {\n+    -1, 0, 1, 1, 2, 2, 2, 2, 3, 3, 3, 3, 3, 3, 3, 3, 4, 4, 4, 4, 4, 4, 4,\n+    4, 4,\n+    4, 4, 4, 4, 4, 4, 4,\n+    5, 5, 5, 5, 5, 5, 5, 5, 5, 5, 5, 5, 5, 5, 5, 5, 5, 5, 5, 5, 5, 5, 5, 5,\n+    5,\n+    5, 5, 5, 5, 5, 5, 5,\n+    6, 6, 6, 6, 6, 6, 6, 6, 6, 6, 6, 6, 6, 6, 6, 6, 6, 6, 6, 6, 6, 6, 6, 6,\n+    6,\n+    6, 6, 6, 6, 6, 6, 6,\n+    6, 6, 6, 6, 6, 6, 6, 6, 6, 6, 6, 6, 6, 6, 6, 6, 6, 6, 6, 6, 6, 6, 6, 6,\n+    6,\n+    6, 6, 6, 6, 6, 6, 6,\n+    7, 7, 7, 7, 7, 7, 7, 7, 7, 7, 7, 7, 7, 7, 7, 7, 7, 7, 7, 7, 7, 7, 7, 7,\n+    7,\n+    7, 7, 7, 7, 7, 7, 7,\n+    7, 7, 7, 7, 7, 7, 7, 7, 7, 7, 7, 7, 7, 7, 7, 7, 7, 7, 7, 7, 7, 7, 7, 7,\n+    7,\n+    7, 7, 7, 7, 7, 7, 7,\n+    7, 7, 7, 7, 7, 7, 7, 7, 7, 7, 7, 7, 7, 7, 7, 7, 7, 7, 7, 7, 7, 7, 7, 7,\n+    7,\n+    7, 7, 7, 7, 7, 7, 7,\n+    7, 7, 7, 7, 7, 7, 7, 7, 7, 7, 7, 7, 7, 7, 7, 7, 7, 7, 7, 7, 7, 7, 7, 7,\n+    7,\n+    7, 7, 7, 7, 7, 7, 7\n+};\n+\n+static __inline__ int ls_bit(int i)\n+{\n+    unsigned int a;\n+    unsigned int x = i & -i;\n+\n+    a = x <= 0xffff ? (x <= 0xff ? 0 : 8) : (x <= 0xffffff ? 16 : 24);\n+    return table[x >> a] + a;\n+}\n+\n+static __inline__ int ms_bit(int i)\n+{\n+    unsigned int a;\n+    unsigned int x = (unsigned int) i;\n+\n+    a = x <= 0xffff ? (x <= 0xff ? 0 : 8) : (x <= 0xffffff ? 16 : 24);\n+    return table[x >> a] + a;\n+}\n+\n+static __inline__ void set_bit(int nr, u32_t * addr)\n+{\n+    addr[nr >> 5] |= 1 << (nr & 0x1f);\n+}\n+\n+static __inline__ void clear_bit(int nr, u32_t * addr)\n+{\n+    addr[nr >> 5] &= ~(1 << (nr & 0x1f));\n+}\n+\n+static __inline__ void MAPPING_SEARCH(size_t * _r, int *_fl, int *_sl)\n+{\n+    int _t;\n+\n+    if (*_r < SMALL_BLOCK) {\n+        *_fl = 0;\n+        *_sl = *_r / (SMALL_BLOCK / MAX_SLI);\n+    } else {\n+        _t = (1 << (ms_bit(*_r) - MAX_LOG2_SLI)) - 1;\n+        *_r = *_r + _t;\n+        *_fl = ms_bit(*_r);\n+        *_sl = (*_r >> (*_fl - MAX_LOG2_SLI)) - MAX_SLI;\n+        *_fl -= FLI_OFFSET;\n+        /*if ((*_fl -= FLI_OFFSET) < 0) // FL wil be always >0!\n+         *_fl = *_sl = 0;\n+         */\n+        *_r &= ~_t;\n+    }\n+}\n+\n+static __inline__ void MAPPING_INSERT(size_t _r, int *_fl, int *_sl)\n+{\n+    if (_r < SMALL_BLOCK) {\n+        *_fl = 0;\n+        *_sl = _r / (SMALL_BLOCK / MAX_SLI);\n+    } else {\n+        *_fl = ms_bit(_r);\n+        *_sl = (_r >> (*_fl - MAX_LOG2_SLI)) - MAX_SLI;\n+        *_fl -= FLI_OFFSET;\n+    }\n+}\n+\n+\n+static __inline__ bhdr_t *FIND_SUITABLE_BLOCK(tlsf_t * _tlsf, int *_fl, int *_sl)\n+{\n+    u32_t _tmp = _tlsf->sl_bitmap[*_fl] & (~0 << *_sl);\n+    bhdr_t *_b = NULL;\n+\n+    if (_tmp) {\n+        *_sl = ls_bit(_tmp);\n+        _b = _tlsf->matrix[*_fl][*_sl];\n+    } else {\n+        *_fl = ls_bit(_tlsf->fl_bitmap & (~0 << (*_fl + 1)));\n+        if (*_fl > 0) {         /* likely */\n+            *_sl = ls_bit(_tlsf->sl_bitmap[*_fl]);\n+            _b = _tlsf->matrix[*_fl][*_sl];\n+        }\n+    }\n+    return _b;\n+}\n+\n+\n+#define EXTRACT_BLOCK_HDR(_b, _tlsf, _fl, _sl) do {\t\t\t\t\t\\\n+\t\t_tlsf -> matrix [_fl] [_sl] = _b -> ptr.free_ptr.next;\t\t\\\n+\t\tif (_tlsf -> matrix[_fl][_sl])\t\t\t\t\t\t\t\t\\\n+\t\t\t_tlsf -> matrix[_fl][_sl] -> ptr.free_ptr.prev = NULL;\t\\\n+\t\telse {\t\t\t\t\t\t\t\t\t\t\t\t\t\t\\\n+\t\t\tclear_bit (_sl, &_tlsf -> sl_bitmap [_fl]);\t\t\t\t\\\n+\t\t\tif (!_tlsf -> sl_bitmap [_fl])\t\t\t\t\t\t\t\\\n+\t\t\t\tclear_bit (_fl, &_tlsf -> fl_bitmap);\t\t\t\t\\\n+\t\t}\t\t\t\t\t\t\t\t\t\t\t\t\t\t\t\\\n+\t\t_b -> ptr.free_ptr.prev =  NULL;\t\t\t\t\\\n+\t\t_b -> ptr.free_ptr.next =  NULL;\t\t\t\t\\\n+\t}while(0)\n+\n+\n+#define EXTRACT_BLOCK(_b, _tlsf, _fl, _sl) do {\t\t\t\t\t\t\t\\\n+\t\tif (_b -> ptr.free_ptr.next)\t\t\t\t\t\t\t\t\t\\\n+\t\t\t_b -> ptr.free_ptr.next -> ptr.free_ptr.prev = _b -> ptr.free_ptr.prev; \\\n+\t\tif (_b -> ptr.free_ptr.prev)\t\t\t\t\t\t\t\t\t\\\n+\t\t\t_b -> ptr.free_ptr.prev -> ptr.free_ptr.next = _b -> ptr.free_ptr.next; \\\n+\t\tif (_tlsf -> matrix [_fl][_sl] == _b) {\t\t\t\t\t\t\t\\\n+\t\t\t_tlsf -> matrix [_fl][_sl] = _b -> ptr.free_ptr.next;\t\t\\\n+\t\t\tif (!_tlsf -> matrix [_fl][_sl]) {\t\t\t\t\t\t\t\\\n+\t\t\t\tclear_bit (_sl, &_tlsf -> sl_bitmap[_fl]);\t\t\t\t\\\n+\t\t\t\tif (!_tlsf -> sl_bitmap [_fl])\t\t\t\t\t\t\t\\\n+\t\t\t\t\tclear_bit (_fl, &_tlsf -> fl_bitmap);\t\t\t\t\\\n+\t\t\t}\t\t\t\t\t\t\t\t\t\t\t\t\t\t\t\\\n+\t\t}\t\t\t\t\t\t\t\t\t\t\t\t\t\t\t\t\\\n+\t\t_b -> ptr.free_ptr.prev = NULL;\t\t\t\t\t\\\n+\t\t_b -> ptr.free_ptr.next = NULL;\t\t\t\t\t\\\n+\t} while(0)\n+\n+#define INSERT_BLOCK(_b, _tlsf, _fl, _sl) do {\t\t\t\t\t\t\t\\\n+\t\t_b -> ptr.free_ptr.prev = NULL; \\\n+\t\t_b -> ptr.free_ptr.next = _tlsf -> matrix [_fl][_sl]; \\\n+\t\tif (_tlsf -> matrix [_fl][_sl])\t\t\t\t\t\t\t\t\t\\\n+\t\t\t_tlsf -> matrix [_fl][_sl] -> ptr.free_ptr.prev = _b;\t\t\\\n+\t\t_tlsf -> matrix [_fl][_sl] = _b;\t\t\t\t\t\t\t\t\\\n+\t\tset_bit (_sl, &_tlsf -> sl_bitmap [_fl]);\t\t\t\t\t\t\\\n+\t\tset_bit (_fl, &_tlsf -> fl_bitmap);\t\t\t\t\t\t\t\t\\\n+\t} while(0)\n+\n+#if USE_SBRK || USE_MMAP\n+static __inline__ void *get_new_area(size_t * size) \n+{\n+    void *area;\n+\n+#if USE_SBRK\n+    area = (void *)sbrk(0);\n+    if (((void *)sbrk(*size)) != ((void *) -1))\n+        return area;\n+#endif\n+\n+#ifndef MAP_ANONYMOUS\n+/* https://dev.openwrt.org/ticket/322 */\n+# define MAP_ANONYMOUS MAP_ANON\n+#endif\n+\n+\n+#if USE_MMAP\n+    *size = ROUNDUP(*size, PAGE_SIZE);\n+    if ((area = mmap(0, *size, PROT_READ | PROT_WRITE, MAP_PRIVATE | MAP_ANONYMOUS, -1, 0)) != MAP_FAILED)\n+        return area;\n+#endif\n+    return ((void *) ~0);\n+}\n+#endif\n+\n+static __inline__ bhdr_t *process_area(void *area, size_t size)\n+{\n+    bhdr_t *b, *lb, *ib;\n+    area_info_t *ai;\n+\n+    ib = (bhdr_t *) area;\n+    ib->size =\n+        (sizeof(area_info_t) <\n+         MIN_BLOCK_SIZE) ? MIN_BLOCK_SIZE : ROUNDUP_SIZE(sizeof(area_info_t)) | USED_BLOCK | PREV_USED;\n+    b = (bhdr_t *) GET_NEXT_BLOCK(ib->ptr.buffer, ib->size & BLOCK_SIZE);\n+    b->size = ROUNDDOWN_SIZE(size - 3 * BHDR_OVERHEAD - (ib->size & BLOCK_SIZE)) | USED_BLOCK | PREV_USED;\n+    b->ptr.free_ptr.prev = b->ptr.free_ptr.next = 0;\n+    lb = GET_NEXT_BLOCK(b->ptr.buffer, b->size & BLOCK_SIZE);\n+    lb->prev_hdr = b;\n+    lb->size = 0 | USED_BLOCK | PREV_FREE;\n+    ai = (area_info_t *) ib->ptr.buffer;\n+    ai->next = 0;\n+    ai->end = lb;\n+    return ib;\n+}\n+\n+/******************************************************************/\n+/******************** Begin of the allocator code *****************/\n+/******************************************************************/\n+\n+static char *mp = NULL;         /* Default memory pool. */\n+\n+/******************************************************************/\n+size_t init_memory_pool(size_t mem_pool_size, void *mem_pool)\n+{\n+/******************************************************************/\n+    tlsf_t *tlsf;\n+    bhdr_t *b, *ib;\n+\n+    if (!mem_pool || !mem_pool_size || mem_pool_size < sizeof(tlsf_t) + BHDR_OVERHEAD * 8) {\n+        ERROR_MSG(\"init_memory_pool (): memory_pool invalid\\n\");\n+        return -1;\n+    }\n+\n+    if (((unsigned long) mem_pool & PTR_MASK)) {\n+        ERROR_MSG(\"init_memory_pool (): mem_pool must be aligned to a word\\n\");\n+        return -1;\n+    }\n+    tlsf = (tlsf_t *) mem_pool;\n+    /* Check if already initialised */\n+    if (tlsf->tlsf_signature == TLSF_SIGNATURE) {\n+        mp = mem_pool;\n+        b = GET_NEXT_BLOCK(mp, ROUNDUP_SIZE(sizeof(tlsf_t)));\n+        return b->size & BLOCK_SIZE;\n+    }\n+\n+    mp = mem_pool;\n+\n+    /* Zeroing the memory pool */\n+    memset(mem_pool, 0, sizeof(tlsf_t));\n+\n+    tlsf->tlsf_signature = TLSF_SIGNATURE;\n+\n+    TLSF_CREATE_LOCK(&tlsf->lock);\n+\n+    ib = process_area(GET_NEXT_BLOCK\n+                      (mem_pool, ROUNDUP_SIZE(sizeof(tlsf_t))), ROUNDDOWN_SIZE(mem_pool_size - sizeof(tlsf_t)));\n+    b = GET_NEXT_BLOCK(ib->ptr.buffer, ib->size & BLOCK_SIZE);\n+    free_ex(b->ptr.buffer, tlsf);\n+    tlsf->area_head = (area_info_t *) ib->ptr.buffer;\n+\n+#if TLSF_STATISTIC\n+    tlsf->used_size = mem_pool_size - (b->size & BLOCK_SIZE);\n+    tlsf->max_size = tlsf->used_size;\n+#endif\n+\n+    return (b->size & BLOCK_SIZE);\n+}\n+\n+/******************************************************************/\n+size_t add_new_area(void *area, size_t area_size, void *mem_pool)\n+{\n+/******************************************************************/\n+    tlsf_t *tlsf = (tlsf_t *) mem_pool;\n+    area_info_t *ptr, *ptr_prev, *ai;\n+    bhdr_t *ib0, *b0, *lb0, *ib1, *b1, *lb1, *next_b;\n+\n+    memset(area, 0, area_size);\n+    ptr = tlsf->area_head;\n+    ptr_prev = 0;\n+\n+    ib0 = process_area(area, area_size);\n+    b0 = GET_NEXT_BLOCK(ib0->ptr.buffer, ib0->size & BLOCK_SIZE);\n+    lb0 = GET_NEXT_BLOCK(b0->ptr.buffer, b0->size & BLOCK_SIZE);\n+\n+    /* Before inserting the new area, we have to merge this area with the\n+       already existing ones */\n+\n+    while (ptr) {\n+        ib1 = (bhdr_t *) ((char *) ptr - BHDR_OVERHEAD);\n+        b1 = GET_NEXT_BLOCK(ib1->ptr.buffer, ib1->size & BLOCK_SIZE);\n+        lb1 = ptr->end;\n+\n+        /* Merging the new area with the next physically contigous one */\n+        if ((unsigned long) ib1 == (unsigned long) lb0 + BHDR_OVERHEAD) {\n+            if (tlsf->area_head == ptr) {\n+                tlsf->area_head = ptr->next;\n+                ptr = ptr->next;\n+            } else {\n+                ptr_prev->next = ptr->next;\n+                ptr = ptr->next;\n+            }\n+\n+            b0->size =\n+                ROUNDDOWN_SIZE((b0->size & BLOCK_SIZE) +\n+                               (ib1->size & BLOCK_SIZE) + 2 * BHDR_OVERHEAD) | USED_BLOCK | PREV_USED;\n+\n+            b1->prev_hdr = b0;\n+            lb0 = lb1;\n+\n+            continue;\n+        }\n+\n+        /* Merging the new area with the previous physically contigous\n+           one */\n+        if ((unsigned long) lb1->ptr.buffer == (unsigned long) ib0) {\n+            if (tlsf->area_head == ptr) {\n+                tlsf->area_head = ptr->next;\n+                ptr = ptr->next;\n+            } else {\n+                ptr_prev->next = ptr->next;\n+                ptr = ptr->next;\n+            }\n+\n+            lb1->size =\n+                ROUNDDOWN_SIZE((b0->size & BLOCK_SIZE) +\n+                               (ib0->size & BLOCK_SIZE) + 2 * BHDR_OVERHEAD) | USED_BLOCK | (lb1->size & PREV_STATE);\n+            next_b = GET_NEXT_BLOCK(lb1->ptr.buffer, lb1->size & BLOCK_SIZE);\n+            next_b->prev_hdr = lb1;\n+            b0 = lb1;\n+            ib0 = ib1;\n+\n+            continue;\n+        }\n+        ptr_prev = ptr;\n+        ptr = ptr->next;\n+    }\n+\n+    /* Inserting the area in the list of linked areas */\n+    ai = (area_info_t *) ib0->ptr.buffer;\n+    ai->next = tlsf->area_head;\n+    ai->end = lb0;\n+    tlsf->area_head = ai;\n+    free_ex(b0->ptr.buffer, mem_pool);\n+    return (b0->size & BLOCK_SIZE);\n+}\n+\n+\n+/******************************************************************/\n+size_t get_used_size(void *mem_pool)\n+{\n+/******************************************************************/\n+#if TLSF_STATISTIC\n+    return ((tlsf_t *) mem_pool)->used_size;\n+#else\n+    return 0;\n+#endif\n+}\n+\n+/******************************************************************/\n+size_t get_max_size(void *mem_pool)\n+{\n+/******************************************************************/\n+#if TLSF_STATISTIC\n+    return ((tlsf_t *) mem_pool)->max_size;\n+#else\n+    return 0;\n+#endif\n+}\n+\n+/******************************************************************/\n+void destroy_memory_pool(void *mem_pool)\n+{\n+/******************************************************************/\n+    tlsf_t *tlsf = (tlsf_t *) mem_pool;\n+\n+    tlsf->tlsf_signature = 0;\n+\n+    TLSF_DESTROY_LOCK(&tlsf->lock);\n+\n+}\n+\n+\n+/******************************************************************/\n+void *tlsf_malloc(size_t size)\n+{\n+/******************************************************************/\n+    void *ret;\n+\n+#if USE_MMAP || USE_SBRK\n+    if (!mp) {\n+        size_t area_size;\n+        void *area;\n+\n+        area_size = sizeof(tlsf_t) + BHDR_OVERHEAD * 8; /* Just a safety constant */\n+        area_size = (area_size > DEFAULT_AREA_SIZE) ? area_size : DEFAULT_AREA_SIZE;\n+        area = get_new_area(&area_size);\n+        if (area == ((void *) ~0))\n+            return NULL;        /* Not enough system memory */\n+        init_memory_pool(area_size, area);\n+    }\n+#endif\n+\n+    TLSF_ACQUIRE_LOCK(&((tlsf_t *)mp)->lock);\n+\n+    ret = malloc_ex(size, mp);\n+\n+    TLSF_RELEASE_LOCK(&((tlsf_t *)mp)->lock);\n+\n+    return ret;\n+}\n+\n+/******************************************************************/\n+void tlsf_free(void *ptr)\n+{\n+/******************************************************************/\n+\n+    TLSF_ACQUIRE_LOCK(&((tlsf_t *)mp)->lock);\n+\n+    free_ex(ptr, mp);\n+\n+    TLSF_RELEASE_LOCK(&((tlsf_t *)mp)->lock);\n+\n+}\n+\n+/******************************************************************/\n+void *tlsf_realloc(void *ptr, size_t size)\n+{\n+/******************************************************************/\n+    void *ret;\n+\n+#if USE_MMAP || USE_SBRK\n+\tif (!mp) {\n+\t\treturn tlsf_malloc(size);\n+\t}\n+#endif\n+\n+    TLSF_ACQUIRE_LOCK(&((tlsf_t *)mp)->lock);\n+\n+    ret = realloc_ex(ptr, size, mp);\n+\n+    TLSF_RELEASE_LOCK(&((tlsf_t *)mp)->lock);\n+\n+    return ret;\n+}\n+\n+/******************************************************************/\n+void *tlsf_calloc(size_t nelem, size_t elem_size)\n+{\n+/******************************************************************/\n+    void *ret;\n+\n+    TLSF_ACQUIRE_LOCK(&((tlsf_t *)mp)->lock);\n+\n+    ret = calloc_ex(nelem, elem_size, mp);\n+\n+    TLSF_RELEASE_LOCK(&((tlsf_t *)mp)->lock);\n+\n+    return ret;\n+}\n+\n+/******************************************************************/\n+void *malloc_ex(size_t size, void *mem_pool)\n+{\n+/******************************************************************/\n+    tlsf_t *tlsf = (tlsf_t *) mem_pool;\n+    bhdr_t *b, *b2, *next_b;\n+    int fl, sl;\n+    size_t tmp_size;\n+\n+    size = (size < MIN_BLOCK_SIZE) ? MIN_BLOCK_SIZE : ROUNDUP_SIZE(size);\n+\n+    /* Rounding up the requested size and calculating fl and sl */\n+    MAPPING_SEARCH(&size, &fl, &sl);\n+\n+    /* Searching a free block, recall that this function changes the values of fl and sl,\n+       so they are not longer valid when the function fails */\n+    b = FIND_SUITABLE_BLOCK(tlsf, &fl, &sl);\n+#if USE_MMAP || USE_SBRK\n+    if (!b) {\n+        size_t area_size;\n+        void *area;\n+        /* Growing the pool size when needed */\n+        area_size = size + BHDR_OVERHEAD * 8;   /* size plus enough room for the requered headers. */\n+        area_size = (area_size > DEFAULT_AREA_SIZE) ? area_size : DEFAULT_AREA_SIZE;\n+        area = get_new_area(&area_size);        /* Call sbrk or mmap */\n+        if (area == ((void *) ~0))\n+            return NULL;        /* Not enough system memory */\n+        add_new_area(area, area_size, mem_pool);\n+        /* Rounding up the requested size and calculating fl and sl */\n+        MAPPING_SEARCH(&size, &fl, &sl);\n+        /* Searching a free block */\n+        b = FIND_SUITABLE_BLOCK(tlsf, &fl, &sl);\n+    }\n+#endif\n+    if (!b)\n+        return NULL;            /* Not found */\n+\n+    EXTRACT_BLOCK_HDR(b, tlsf, fl, sl);\n+\n+    /*-- found: */\n+    next_b = GET_NEXT_BLOCK(b->ptr.buffer, b->size & BLOCK_SIZE);\n+    /* Should the block be split? */\n+    tmp_size = (b->size & BLOCK_SIZE) - size;\n+    if (tmp_size >= sizeof(bhdr_t)) {\n+        tmp_size -= BHDR_OVERHEAD;\n+        b2 = GET_NEXT_BLOCK(b->ptr.buffer, size);\n+        b2->size = tmp_size | FREE_BLOCK | PREV_USED;\n+        next_b->prev_hdr = b2;\n+        MAPPING_INSERT(tmp_size, &fl, &sl);\n+        INSERT_BLOCK(b2, tlsf, fl, sl);\n+\n+        b->size = size | (b->size & PREV_STATE);\n+    } else {\n+        next_b->size &= (~PREV_FREE);\n+        b->size &= (~FREE_BLOCK);       /* Now it's used */\n+    }\n+\n+    TLSF_ADD_SIZE(tlsf, b);\n+\n+    return (void *) b->ptr.buffer;\n+}\n+\n+/******************************************************************/\n+void free_ex(void *ptr, void *mem_pool)\n+{\n+/******************************************************************/\n+    tlsf_t *tlsf = (tlsf_t *) mem_pool;\n+    bhdr_t *b, *tmp_b;\n+    int fl = 0, sl = 0;\n+\n+    if (!ptr) {\n+        return;\n+    }\n+    b = (bhdr_t *) ((char *) ptr - BHDR_OVERHEAD);\n+    b->size |= FREE_BLOCK;\n+\n+    TLSF_REMOVE_SIZE(tlsf, b);\n+\n+    b->ptr.free_ptr.prev = NULL;\n+    b->ptr.free_ptr.next = NULL;\n+    tmp_b = GET_NEXT_BLOCK(b->ptr.buffer, b->size & BLOCK_SIZE);\n+    if (tmp_b->size & FREE_BLOCK) {\n+        MAPPING_INSERT(tmp_b->size & BLOCK_SIZE, &fl, &sl);\n+        EXTRACT_BLOCK(tmp_b, tlsf, fl, sl);\n+        b->size += (tmp_b->size & BLOCK_SIZE) + BHDR_OVERHEAD;\n+    }\n+    if (b->size & PREV_FREE) {\n+        tmp_b = b->prev_hdr;\n+        MAPPING_INSERT(tmp_b->size & BLOCK_SIZE, &fl, &sl);\n+        EXTRACT_BLOCK(tmp_b, tlsf, fl, sl);\n+        tmp_b->size += (b->size & BLOCK_SIZE) + BHDR_OVERHEAD;\n+        b = tmp_b;\n+    }\n+    MAPPING_INSERT(b->size & BLOCK_SIZE, &fl, &sl);\n+    INSERT_BLOCK(b, tlsf, fl, sl);\n+\n+    tmp_b = GET_NEXT_BLOCK(b->ptr.buffer, b->size & BLOCK_SIZE);\n+    tmp_b->size |= PREV_FREE;\n+    tmp_b->prev_hdr = b;\n+}\n+\n+/******************************************************************/\n+void *realloc_ex(void *ptr, size_t new_size, void *mem_pool)\n+{\n+/******************************************************************/\n+    tlsf_t *tlsf = (tlsf_t *) mem_pool;\n+    void *ptr_aux;\n+    unsigned int cpsize;\n+    bhdr_t *b, *tmp_b, *next_b;\n+    int fl, sl;\n+    size_t tmp_size;\n+\n+    if (!ptr) {\n+        if (new_size)\n+            return (void *) malloc_ex(new_size, mem_pool);\n+        if (!new_size)\n+            return NULL;\n+    } else if (!new_size) {\n+        free_ex(ptr, mem_pool);\n+        return NULL;\n+    }\n+\n+    b = (bhdr_t *) ((char *) ptr - BHDR_OVERHEAD);\n+    next_b = GET_NEXT_BLOCK(b->ptr.buffer, b->size & BLOCK_SIZE);\n+    new_size = (new_size < MIN_BLOCK_SIZE) ? MIN_BLOCK_SIZE : ROUNDUP_SIZE(new_size);\n+    tmp_size = (b->size & BLOCK_SIZE);\n+    if (new_size <= tmp_size) {\n+\tTLSF_REMOVE_SIZE(tlsf, b);\n+        if (next_b->size & FREE_BLOCK) {\n+            MAPPING_INSERT(next_b->size & BLOCK_SIZE, &fl, &sl);\n+            EXTRACT_BLOCK(next_b, tlsf, fl, sl);\n+            tmp_size += (next_b->size & BLOCK_SIZE) + BHDR_OVERHEAD;\n+            next_b = GET_NEXT_BLOCK(next_b->ptr.buffer, next_b->size & BLOCK_SIZE);\n+            /* We allways reenter this free block because tmp_size will\n+               be greater then sizeof (bhdr_t) */\n+        }\n+        tmp_size -= new_size;\n+        if (tmp_size >= sizeof(bhdr_t)) {\n+            tmp_size -= BHDR_OVERHEAD;\n+            tmp_b = GET_NEXT_BLOCK(b->ptr.buffer, new_size);\n+            tmp_b->size = tmp_size | FREE_BLOCK | PREV_USED;\n+            next_b->prev_hdr = tmp_b;\n+            next_b->size |= PREV_FREE;\n+            MAPPING_INSERT(tmp_size, &fl, &sl);\n+            INSERT_BLOCK(tmp_b, tlsf, fl, sl);\n+            b->size = new_size | (b->size & PREV_STATE);\n+        }\n+\tTLSF_ADD_SIZE(tlsf, b);\n+        return (void *) b->ptr.buffer;\n+    }\n+    if ((next_b->size & FREE_BLOCK)) {\n+        if (new_size <= (tmp_size + (next_b->size & BLOCK_SIZE))) {\n+\t\t\tTLSF_REMOVE_SIZE(tlsf, b);\n+            MAPPING_INSERT(next_b->size & BLOCK_SIZE, &fl, &sl);\n+            EXTRACT_BLOCK(next_b, tlsf, fl, sl);\n+            b->size += (next_b->size & BLOCK_SIZE) + BHDR_OVERHEAD;\n+            next_b = GET_NEXT_BLOCK(b->ptr.buffer, b->size & BLOCK_SIZE);\n+            next_b->prev_hdr = b;\n+            next_b->size &= ~PREV_FREE;\n+            tmp_size = (b->size & BLOCK_SIZE) - new_size;\n+            if (tmp_size >= sizeof(bhdr_t)) {\n+                tmp_size -= BHDR_OVERHEAD;\n+                tmp_b = GET_NEXT_BLOCK(b->ptr.buffer, new_size);\n+                tmp_b->size = tmp_size | FREE_BLOCK | PREV_USED;\n+                next_b->prev_hdr = tmp_b;\n+                next_b->size |= PREV_FREE;\n+                MAPPING_INSERT(tmp_size, &fl, &sl);\n+                INSERT_BLOCK(tmp_b, tlsf, fl, sl);\n+                b->size = new_size | (b->size & PREV_STATE);\n+            }\n+\t\t\tTLSF_ADD_SIZE(tlsf, b);\n+            return (void *) b->ptr.buffer;\n+        }\n+    }\n+\n+    if (!(ptr_aux = malloc_ex(new_size, mem_pool))){\n+        return NULL;\n+    }      \n+    \n+    cpsize = ((b->size & BLOCK_SIZE) > new_size) ? new_size : (b->size & BLOCK_SIZE);\n+\n+    memcpy(ptr_aux, ptr, cpsize);\n+\n+    free_ex(ptr, mem_pool);\n+    return ptr_aux;\n+}\n+\n+\n+/******************************************************************/\n+void *calloc_ex(size_t nelem, size_t elem_size, void *mem_pool)\n+{\n+/******************************************************************/\n+    void *ptr;\n+\n+    if (nelem <= 0 || elem_size <= 0)\n+        return NULL;\n+\n+    if (!(ptr = malloc_ex(nelem * elem_size, mem_pool)))\n+        return NULL;\n+    memset(ptr, 0, nelem * elem_size);\n+\n+    return ptr;\n+}\n+\n+\n+\n+#if _DEBUG_TLSF_\n+\n+/***************  DEBUG FUNCTIONS   **************/\n+\n+/* The following functions have been designed to ease the debugging of */\n+/* the TLSF  structure.  For non-developing  purposes, it may  be they */\n+/* haven't too much worth.  To enable them, _DEBUG_TLSF_ must be set.  */\n+\n+extern void dump_memory_region(unsigned char *mem_ptr, unsigned int size);\n+extern void print_block(bhdr_t * b);\n+extern void print_tlsf(tlsf_t * tlsf);\n+void print_all_blocks(tlsf_t * tlsf);\n+\n+void dump_memory_region(unsigned char *mem_ptr, unsigned int size)\n+{\n+\n+    unsigned long begin = (unsigned long) mem_ptr;\n+    unsigned long end = (unsigned long) mem_ptr + size;\n+    int column = 0;\n+\n+    begin >>= 2;\n+    begin <<= 2;\n+\n+    end >>= 2;\n+    end++;\n+    end <<= 2;\n+\n+    PRINT_MSG(\"\\nMemory region dumped: 0x%lx - 0x%lx\\n\\n\", begin, end);\n+\n+    column = 0;\n+    PRINT_MSG(\"0x%lx \", begin);\n+\n+    while (begin < end) {\n+        if (((unsigned char *) begin)[0] == 0)\n+            PRINT_MSG(\"00\");\n+        else\n+            PRINT_MSG(\"%02x\", ((unsigned char *) begin)[0]);\n+        if (((unsigned char *) begin)[1] == 0)\n+            PRINT_MSG(\"00 \");\n+        else\n+            PRINT_MSG(\"%02x \", ((unsigned char *) begin)[1]);\n+        begin += 2;\n+        column++;\n+        if (column == 8) {\n+            PRINT_MSG(\"\\n0x%lx \", begin);\n+            column = 0;\n+        }\n+\n+    }\n+    PRINT_MSG(\"\\n\\n\");\n+}\n+\n+void print_block(bhdr_t * b)\n+{\n+    if (!b)\n+        return;\n+    PRINT_MSG(\">> [%p] (\", b);\n+    if ((b->size & BLOCK_SIZE))\n+        PRINT_MSG(\"%lu bytes, \", (unsigned long) (b->size & BLOCK_SIZE));\n+    else\n+        PRINT_MSG(\"sentinel, \");\n+    if ((b->size & BLOCK_STATE) == FREE_BLOCK)\n+        PRINT_MSG(\"free [%p, %p], \", b->ptr.free_ptr.prev, b->ptr.free_ptr.next);\n+    else\n+        PRINT_MSG(\"used, \");\n+    if ((b->size & PREV_STATE) == PREV_FREE)\n+        PRINT_MSG(\"prev. free [%p])\\n\", b->prev_hdr);\n+    else\n+        PRINT_MSG(\"prev used)\\n\");\n+}\n+\n+void print_tlsf(tlsf_t * tlsf)\n+{\n+    bhdr_t *next;\n+    int i, j;\n+\n+    PRINT_MSG(\"\\nTLSF at %p\\n\", tlsf);\n+\n+    PRINT_MSG(\"FL bitmap: 0x%x\\n\\n\", (unsigned) tlsf->fl_bitmap);\n+\n+    for (i = 0; i < REAL_FLI; i++) {\n+        if (tlsf->sl_bitmap[i])\n+            PRINT_MSG(\"SL bitmap 0x%x\\n\", (unsigned) tlsf->sl_bitmap[i]);\n+        for (j = 0; j < MAX_SLI; j++) {\n+            next = tlsf->matrix[i][j];\n+            if (next)\n+                PRINT_MSG(\"-> [%d][%d]\\n\", i, j);\n+            while (next) {\n+                print_block(next);\n+                next = next->ptr.free_ptr.next;\n+            }\n+        }\n+    }\n+}\n+\n+void print_all_blocks(tlsf_t * tlsf)\n+{\n+    area_info_t *ai;\n+    bhdr_t *next;\n+    PRINT_MSG(\"\\nTLSF at %p\\nALL BLOCKS\\n\\n\", tlsf);\n+    ai = tlsf->area_head;\n+    while (ai) {\n+        next = (bhdr_t *) ((char *) ai - BHDR_OVERHEAD);\n+        while (next) {\n+            print_block(next);\n+            if ((next->size & BLOCK_SIZE))\n+                next = GET_NEXT_BLOCK(next->ptr.buffer, next->size & BLOCK_SIZE);\n+            else\n+                next = NULL;\n+        }\n+        ai = ai->next;\n+    }\n+}\n+\n+#endif\n+\n+#ifdef __cplusplus\n+}\n+#endif"
        }
      ]
    }
  ]
}