{
  "_meta": {
    "fetched_at": "2026-03-03T22:47:38Z",
    "source": "github_rest",
    "endpoint": "/repos/{owner}/{repo}/forks",
    "owner": "gazebo-release",
    "repo": "gz_rendering_vendor",
    "per_page": 100
  },
  "data": [
    {
      "forked_at": "2025-07-30T16:01:34Z",
      "owner": "pszenher",
      "full_name": "pszenher/gz_rendering_vendor",
      "html_url": "https://github.com/pszenher/gz_rendering_vendor"
    },
    {
      "forked_at": "2024-09-18T20:57:08Z",
      "owner": "nwn",
      "full_name": "nwn/gz_rendering_vendor",
      "html_url": "https://github.com/nwn/gz_rendering_vendor"
    }
  ]
}