{
  "_meta": {
    "fetched_at": "2026-03-03T20:55:53Z",
    "source": "github_rest",
    "endpoint": "/repos/{owner}/{repo}/forks",
    "owner": "mikeferguson",
    "repo": "simple_grasping",
    "per_page": 100
  },
  "data": [
    {
      "forked_at": "2025-06-11T09:33:42Z",
      "owner": "ahcorde",
      "full_name": "ahcorde/simple_grasping",
      "html_url": "https://github.com/ahcorde/simple_grasping"
    },
    {
      "forked_at": "2025-05-13T07:50:39Z",
      "owner": "xiayule01",
      "full_name": "xiayule01/simple_grasping",
      "html_url": "https://github.com/xiayule01/simple_grasping"
    },
    {
      "forked_at": "2024-11-26T01:29:03Z",
      "owner": "kuralme",
      "full_name": "kuralme/simple_grasping",
      "html_url": "https://github.com/kuralme/simple_grasping"
    },
    {
      "forked_at": "2024-11-18T09:47:54Z",
      "owner": "jeeveshreddy",
      "full_name": "jeeveshreddy/simple_grasping",
      "html_url": "https://github.com/jeeveshreddy/simple_grasping"
    },
    {
      "forked_at": "2024-10-27T10:46:12Z",
      "owner": "xuannadi",
      "full_name": "xuannadi/simple_grasping",
      "html_url": "https://github.com/xuannadi/simple_grasping"
    },
    {
      "forked_at": "2024-09-11T16:51:45Z",
      "owner": "WikiGenius",
      "full_name": "WikiGenius/simple_grasping",
      "html_url": "https://github.com/WikiGenius/simple_grasping"
    },
    {
      "forked_at": "2023-06-25T01:10:17Z",
      "owner": "robofeiathome",
      "full_name": "robofeiathome/simple_grasping",
      "html_url": "https://github.com/robofeiathome/simple_grasping"
    },
    {
      "forked_at": "2023-05-14T09:26:13Z",
      "owner": "ahmedosama07",
      "full_name": "ahmedosama07/simple_grasping",
      "html_url": "https://github.com/ahmedosama07/simple_grasping"
    },
    {
      "forked_at": "2023-04-19T20:38:25Z",
      "owner": "130s",
      "full_name": "130s/simple_grasping",
      "html_url": "https://github.com/130s/simple_grasping"
    },
    {
      "forked_at": "2023-01-21T06:31:03Z",
      "owner": "ramasingam",
      "full_name": "ramasingam/simple_grasping",
      "html_url": "https://github.com/ramasingam/simple_grasping"
    },
    {
      "forked_at": "2022-09-23T06:50:43Z",
      "owner": "robot-xbrain",
      "full_name": "robot-xbrain/simple_grasping",
      "html_url": "https://github.com/robot-xbrain/simple_grasping"
    },
    {
      "forked_at": "2022-06-06T21:27:37Z",
      "owner": "quasi-robotics",
      "full_name": "quasi-robotics/simple_grasping",
      "html_url": "https://github.com/quasi-robotics/simple_grasping"
    },
    {
      "forked_at": "2022-02-13T19:46:08Z",
      "owner": "Horry-Lee",
      "full_name": "Horry-Lee/simple_grasping",
      "html_url": "https://github.com/Horry-Lee/simple_grasping"
    },
    {
      "forked_at": "2021-09-01T07:45:01Z",
      "owner": "siyeonkim33",
      "full_name": "siyeonkim33/simple_grasping",
      "html_url": "https://github.com/siyeonkim33/simple_grasping"
    },
    {
      "forked_at": "2021-04-15T17:22:27Z",
      "owner": "christian-rauch",
      "full_name": "christian-rauch/simple_grasping",
      "html_url": "https://github.com/christian-rauch/simple_grasping"
    },
    {
      "forked_at": "2020-12-20T17:48:01Z",
      "owner": "vijirammech",
      "full_name": "vijirammech/simple_grasping",
      "html_url": "https://github.com/vijirammech/simple_grasping"
    },
    {
      "forked_at": "2020-09-05T19:41:31Z",
      "owner": "yuchen-x",
      "full_name": "yuchen-x/simple_grasping",
      "html_url": "https://github.com/yuchen-x/simple_grasping"
    },
    {
      "forked_at": "2020-07-14T14:04:16Z",
      "owner": "mahmoud-a-ali",
      "full_name": "mahmoud-a-ali/simple_grasping",
      "html_url": "https://github.com/mahmoud-a-ali/simple_grasping"
    },
    {
      "forked_at": "2020-07-09T08:34:13Z",
      "owner": "xingyi122",
      "full_name": "xingyi122/simple_grasping",
      "html_url": "https://github.com/xingyi122/simple_grasping"
    },
    {
      "forked_at": "2020-05-27T13:16:51Z",
      "owner": "amdshameer",
      "full_name": "amdshameer/simple_grasping",
      "html_url": "https://github.com/amdshameer/simple_grasping"
    },
    {
      "forked_at": "2020-04-19T19:41:55Z",
      "owner": "hchittanuru3",
      "full_name": "hchittanuru3/simple_grasping",
      "html_url": "https://github.com/hchittanuru3/simple_grasping"
    },
    {
      "forked_at": "2020-04-13T18:55:45Z",
      "owner": "708yamaguchi",
      "full_name": "708yamaguchi/simple_grasping",
      "html_url": "https://github.com/708yamaguchi/simple_grasping"
    },
    {
      "forked_at": "2020-02-20T15:12:06Z",
      "owner": "yani-rl-ai",
      "full_name": "yani-rl-ai/simple_grasping",
      "html_url": "https://github.com/yani-rl-ai/simple_grasping"
    },
    {
      "forked_at": "2019-07-25T06:42:36Z",
      "owner": "slugflow",
      "full_name": "slugflow/simple_grasping",
      "html_url": "https://github.com/slugflow/simple_grasping"
    },
    {
      "forked_at": "2019-05-17T11:16:45Z",
      "owner": "me2george",
      "full_name": "me2george/simple_grasping",
      "html_url": "https://github.com/me2george/simple_grasping"
    },
    {
      "forked_at": "2018-08-16T13:56:22Z",
      "owner": "banerjs",
      "full_name": "banerjs/simple_grasping",
      "html_url": "https://github.com/banerjs/simple_grasping"
    },
    {
      "forked_at": "2018-08-14T22:48:01Z",
      "owner": "mikaelarguedas",
      "full_name": "mikaelarguedas/simple_grasping",
      "html_url": "https://github.com/mikaelarguedas/simple_grasping"
    },
    {
      "forked_at": "2018-03-02T22:51:38Z",
      "owner": "hzyjerry",
      "full_name": "hzyjerry/simple_grasping",
      "html_url": "https://github.com/hzyjerry/simple_grasping"
    },
    {
      "forked_at": "2018-03-02T02:17:44Z",
      "owner": "tttor",
      "full_name": "tttor/simple_grasping",
      "html_url": "https://github.com/tttor/simple_grasping"
    },
    {
      "forked_at": "2017-06-17T03:40:21Z",
      "owner": "haoyihan",
      "full_name": "haoyihan/simple_grasping",
      "html_url": "https://github.com/haoyihan/simple_grasping"
    },
    {
      "forked_at": "2016-10-13T14:37:23Z",
      "owner": "hishamcg",
      "full_name": "hishamcg/simple_grasping",
      "html_url": "https://github.com/hishamcg/simple_grasping"
    },
    {
      "forked_at": "2016-04-25T07:50:43Z",
      "owner": "amoliu",
      "full_name": "amoliu/simple_grasping",
      "html_url": "https://github.com/amoliu/simple_grasping"
    },
    {
      "forked_at": "2016-04-24T01:15:32Z",
      "owner": "SiChiTong",
      "full_name": "SiChiTong/simple_grasping",
      "html_url": "https://github.com/SiChiTong/simple_grasping"
    },
    {
      "forked_at": "2015-12-05T08:41:24Z",
      "owner": "b2220333",
      "full_name": "b2220333/simple_grasping",
      "html_url": "https://github.com/b2220333/simple_grasping"
    },
    {
      "forked_at": "2015-10-19T19:05:19Z",
      "owner": "hanhongsun",
      "full_name": "hanhongsun/simple_grasping",
      "html_url": "https://github.com/hanhongsun/simple_grasping"
    },
    {
      "forked_at": "2015-08-10T08:50:24Z",
      "owner": "ferherranz",
      "full_name": "ferherranz/simple_grasping",
      "html_url": "https://github.com/ferherranz/simple_grasping"
    },
    {
      "forked_at": "2015-03-18T21:19:36Z",
      "owner": "ablasdel",
      "full_name": "ablasdel/simple_grasping",
      "html_url": "https://github.com/ablasdel/simple_grasping"
    }
  ]
}